{"nodes": {"286331": {"name": "département français", "type": 777, "weight": 121}, "37684227": {"name": "département de France", "type": 1, "weight": 46}, "237669": {"name": "département>163529", "type": 1, "weight": 29}, "137865": {"name": "cours d'eau", "type": 1, "weight": 1720}, "111394": {"name": "département", "type": 1, "weight": 6776}, "49154": {"name": "rivière", "type": 1, "weight": 5351}, "9264356": {"name": "en:stream", "type": 1, "weight": 25}, "10329446": {"name": "rivière française", "type": 1, "weight": 27}, "15230252": {"name": "en:running stream", "type": 1, "weight": 25}, "12503940": {"name": "en:river", "type": 1, "weight": 25}, "145260": {"name": "Drôme", "type": 1, "weight": 2015}}, "relations": [{"node1": 145260, "node2": 49154, "type": 6, "weight": 33.0}, {"node1": 145260, "node2": 111394, "type": 6, "weight": 64.0}, {"node1": 145260, "node2": 137865, "type": 6, "weight": 29.0}, {"node1": 145260, "node2": 237669, "type": 6, "weight": 99.0}, {"node1": 145260, "node2": 286331, "type": 6, "weight": 15.0}, {"node1": 145260, "node2": 9264356, "type": 6, "weight": 36.0}, {"node1": 145260, "node2": 10329446, "type": 6, "weight": 15.0}, {"node1": 145260, "node2": 12503940, "type": 6, "weight": 36.0}, {"node1": 145260, "node2": 15230252, "type": 6, "weight": 25.0}, {"node1": 145260, "node2": 37684227, "type": 6, "weight": 70.0}]}