{"nodes": {"243120641": {"name": "concept abstrait", "type": 1, "weight": 40}, "213171": {"name": "activité humaine", "type": 1, "weight": 327}, "41002": {"name": "résultat", "type": 1, "weight": 14045}, "5663": {"name": "processus", "type": 1, "weight": 11563}, "3695": {"name": "art", "type": 1, "weight": 16581}, "144938": {"name": "oeuvre", "type": 1, "weight": 4663}, "143497": {"name": "création", "type": 1, "weight": 10406}, "112929": {"name": "action", "type": 1, "weight": 18866}}, "relations": [{"node1": 143497, "node2": 3695, "type": 6, "weight": 32.0}, {"node1": 143497, "node2": 5663, "type": 6, "weight": 42.0}, {"node1": 143497, "node2": 41002, "type": 6, "weight": 50.0}, {"node1": 143497, "node2": 112929, "type": 6, "weight": 28.0}, {"node1": 143497, "node2": 144938, "type": 6, "weight": 22.0}, {"node1": 143497, "node2": 213171, "type": 6, "weight": 31.0}, {"node1": 143497, "node2": 243120641, "type": 6, "weight": 40.0}]}