{"nodes": {"25260": {"name": "missionnariat", "type": 1, "weight": 50}, "25282": {"name": "défenseur", "type": 1, "weight": 2399}, "4146": {"name": "lazariste", "type": 1, "weight": 51}, "7724": {"name": "charger", "type": 1, "weight": 3627}, "104591": {"name": "pasteur", "type": 1, "weight": 1293}, "18128": {"name": "élan", "type": 1, "weight": 485}, "108658": {"name": "Anna", "type": 1, "weight": 2530}, "108463": {"name": "ventre", "type": 1, "weight": 3847}, "17927": {"name": "haine", "type": 1, "weight": 4297}, "50081": {"name": "Gabriel Lalemant", "type": 1, "weight": 50}, "116546": {"name": "Chrétien", "type": 1, "weight": 58}, "25760": {"name": "guppy", "type": 1, "weight": 50}, "1384": {"name": "vivant", "type": 1, "weight": 7085}, "91794": {"name": "tétrapode", "type": 1, "weight": 142}, "65081": {"name": "organisme vivant", "type": 1, "weight": 283}, "81934": {"name": "main", "type": 1, "weight": 40445}, "19356": {"name": "sexe", "type": 1, "weight": 6819}, "30387": {"name": "église", "type": 1, "weight": 5183}, "103405": {"name": "indifférence", "type": 1, "weight": 981}, "36040": {"name": "propagation", "type": 1, "weight": 3113}, "102499": {"name": "évangélisation", "type": 1, "weight": 160}, "59874": {"name": "envoyé", "type": 1, "weight": 3337}, "90830": {"name": "dégoût", "type": 1, "weight": 1126}, "87789": {"name": "coelomate", "type": 1, "weight": 56}, "71624": {"name": "être vivant", "type": 1, "weight": 2635}, "63235": {"name": "mammifère", "type": 1, "weight": 4180}, "60835": {"name": "terreur", "type": 1, "weight": 2444}, "12037": {"name": "enseigner", "type": 1, "weight": 2704}, "32735": {"name": "poumons", "type": 1, "weight": 663}, "23114": {"name": "anxiété", "type": 1, "weight": 3852}, "120892": {"name": "méfiance", "type": 1, "weight": 1844}, "107477": {"name": "nez", "type": 1, "weight": 4685}, "47918": {"name": "boire", "type": 1, "weight": 8837}, "126388": {"name": "articulation", "type": 1, "weight": 1306}, "22264": {"name": "colère", "type": 1, "weight": 6009}, "7045": {"name": "propagateur", "type": 1, "weight": 59}, "81680": {"name": "époque", "type": 1, "weight": 10026}, "34898": {"name": "pied", "type": 1, "weight": 21583}, "103311": {"name": "système nerveux", "type": 1, "weight": 1080}, "29859": {"name": "mal-être", "type": 1, "weight": 443}, "45671": {"name": "catholique", "type": 1, "weight": 3868}, "95943": {"name": "flûte à bec", "type": 1, "weight": 60}, "77008": {"name": "yeux", "type": 1, "weight": 36068}, "47249": {"name": "Isaac Jogues", "type": 1, "weight": 50}, "99220": {"name": "hétérotrophe", "type": 1, "weight": 89}, "114327": {"name": "acide désoxyribonucléique", "type": 1, "weight": 214}, "74846": {"name": "corps", "type": 1, "weight": 16806}, "13788": {"name": "représentant", "type": 1, "weight": 5402}, "64238": {"name": "noir", "type": 1, "weight": 13771}, "15196": {"name": "blanc", "type": 1, "weight": 12871}, "33882": {"name": "se nourrir", "type": 1, "weight": 891}, "77424": {"name": "oeil", "type": 1, "weight": 7896}, "124600": {"name": "mourir", "type": 1, "weight": 11773}, "126285": {"name": "dos", "type": 1, "weight": 5583}, "20269": {"name": "chargé", "type": 1, "weight": 4302}, "60152": {"name": "bassin", "type": 1, "weight": 3386}, "117095": {"name": "zoologie", "type": 1, "weight": 2793}, "83944": {"name": "nerf", "type": 1, "weight": 972}, "39031": {"name": "cerveau", "type": 1, "weight": 8977}, "96211": {"name": "coeur", "type": 1, "weight": 3911}, "63018": {"name": "prière", "type": 1, "weight": 4203}, "82489": {"name": "frustration", "type": 1, "weight": 1406}, "2299": {"name": "coelome", "type": 1, "weight": 60}, "111410": {"name": "religieux", "type": 1, "weight": 4306}, "53002": {"name": "sexualité", "type": 1, "weight": 3367}, "14563": {"name": "mission", "type": 1, "weight": 9795}, "9626": {"name": "devenir", "type": 1, "weight": 35377}, "2442": {"name": "vivre", "type": 1, "weight": 18756}, "57791": {"name": "position", "type": 1, "weight": 9331}, "47319": {"name": "colonne vertébrale", "type": 1, "weight": 462}, "105814": {"name": "regarder", "type": 1, "weight": 36489}, "626": {"name": "peur", "type": 1, "weight": 13441}, "14330": {"name": "satisfaction", "type": 1, "weight": 7748}, "101018": {"name": "gnathostome", "type": 1, "weight": 96}, "74860": {"name": "homme", "type": 1, "weight": 109680}, "75065": {"name": "accomplir", "type": 1, "weight": 2566}, "100835": {"name": "islam", "type": 1, "weight": 1161}, "29672": {"name": "croyance", "type": 1, "weight": 5118}, "16747": {"name": "adn", "type": 1, "weight": 931}, "73890": {"name": "religion", "type": 1, "weight": 11019}, "22243": {"name": "pays", "type": 1, "weight": 29109}, "55823": {"name": "métazoaire", "type": 1, "weight": 212}, "36642": {"name": "aventure", "type": 1, "weight": 6998}, "24247": {"name": "service", "type": 1, "weight": 17039}, "16110": {"name": "bouche", "type": 1, "weight": 8066}, "116477": {"name": "personne", "type": 1, "weight": 35594}, "94431": {"name": "neck", "type": 1, "weight": 88}, "24956": {"name": "être humain", "type": 1, "weight": 2981}, "20528": {"name": "hominidé", "type": 1, "weight": 236}, "115304": {"name": "deutérostomien", "type": 1, "weight": 123}, "103416": {"name": "euthérien", "type": 1, "weight": 61}, "54794": {"name": "eucaryote", "type": 1, "weight": 272}, "57933": {"name": "guerre", "type": 1, "weight": 23368}, "122864": {"name": "mort", "type": 1, "weight": 21064}, "53688": {"name": "activité", "type": 1, "weight": 10784}, "102633": {"name": "soldat", "type": 1, "weight": 6148}, "86640": {"name": "vertébré", "type": 1, "weight": 1089}, "110773": {"name": "amniote", "type": 1, "weight": 94}, "33840": {"name": "primate", "type": 1, "weight": 457}, "79255": {"name": "enseignement", "type": 1, "weight": 6936}, "15279": {"name": "engagement", "type": 1, "weight": 42517}, "26363": {"name": "bras", "type": 1, "weight": 11281}, "86404": {"name": "foi", "type": 1, "weight": 6472}, "102452": {"name": "spiritualité", "type": 1, "weight": 1951}, "22885": {"name": "culture", "type": 1, "weight": 54946}, "85755": {"name": "secteur", "type": 1, "weight": 7148}, "91691": {"name": "surprise", "type": 1, "weight": 3439}, "28453": {"name": "bonheur", "type": 1, "weight": 16648}, "109785": {"name": "peau", "type": 1, "weight": 7573}, "57221": {"name": "joie", "type": 1, "weight": 14510}, "61404": {"name": "prédicant", "type": 1, "weight": 51}, "4552": {"name": "inquiétude", "type": 1, "weight": 3718}, "49337": {"name": "crainte", "type": 1, "weight": 3371}, "44412": {"name": "Mère Teresa", "type": 1, "weight": 71}, "37298": {"name": "amour", "type": 1, "weight": 33666}, "43601": {"name": "se reproduire", "type": 1, "weight": 1698}, "43253": {"name": "dormir", "type": 1, "weight": 10615}, "17559": {"name": "animal", "type": 1, "weight": 18949}, "13369": {"name": "être", "type": 1, "weight": 925579}, "118203": {"name": "corps humain", "type": 1, "weight": 671}, "35143": {"name": "biologie", "type": 1, "weight": 6988}, "68439": {"name": "individu", "type": 1, "weight": 11856}, "20202": {"name": "tristesse", "type": 1, "weight": 5168}, "3376": {"name": "membres", "type": 1, "weight": 5302}, "49293": {"name": "humain", "type": 1, "weight": 11040}, "15730": {"name": "Paulin", "type": 1, "weight": 51}, "6184": {"name": "apostolat", "type": 1, "weight": 75}, "78472": {"name": "évangélisateur", "type": 1, "weight": 53}, "22218": {"name": "camp", "type": 1, "weight": 4311}, "91737": {"name": "moniale", "type": 1, "weight": 69}, "19452": {"name": "François Xavier", "type": 1, "weight": 50}, "34010": {"name": "religieusement", "type": 1, "weight": 118}, "71264": {"name": "doctrinaire", "type": 1, "weight": 72}, "134247": {"name": "missionnaire", "type": 1, "weight": 196}, "98651": {"name": "prosélyte", "type": 1, "weight": 73}, "115331": {"name": "sermonnaire", "type": 1, "weight": 50}, "31882": {"name": "prêcher", "type": 1, "weight": 156}, "115262": {"name": "James Cameron", "type": 1, "weight": 201}, "120157": {"name": "règne animal", "type": 1, "weight": 309}, "29892": {"name": "conversion", "type": 1, "weight": 2948}, "13883": {"name": "humanitaire", "type": 1, "weight": 2004}, "72477": {"name": "bonne soeur", "type": 1, "weight": 150}, "101689": {"name": "être animé", "type": 1, "weight": 86}, "95982": {"name": "évangéliser", "type": 1, "weight": 78}, "88344": {"name": "prostitution", "type": 1, "weight": 814}, "39940": {"name": "prédication", "type": 1, "weight": 64}, "4209": {"name": "Louis Bertrand", "type": 1, "weight": 50}, "104265": {"name": "prédicateur", "type": 1, "weight": 132}, "101172": {"name": "Paul", "type": 1, "weight": 4101}, "97748": {"name": "orateur", "type": 1, "weight": 537}, "95422": {"name": "cou", "type": 1, "weight": 3564}, "4979": {"name": "David Livingstone", "type": 1, "weight": 57}, "93773": {"name": "bouffée", "type": 1, "weight": 76}, "46505": {"name": "enseignant", "type": 1, "weight": 4214}, "69283": {"name": "apôtre", "type": 1, "weight": 536}, "105621": {"name": "vivipare", "type": 1, "weight": 91}, "78119": {"name": "se sacrifier", "type": 1, "weight": 99}, "7976": {"name": "élu", "type": 1, "weight": 4585}, "115463": {"name": "évangélique", "type": 1, "weight": 155}}, "relations": [{"node1": 134247, "node2": 626, "type": 32, "weight": 13.0}, {"node1": 134247, "node2": 1384, "type": 17, "weight": 32.0}, {"node1": 134247, "node2": 2299, "type": 9, "weight": 25.0}, {"node1": 134247, "node2": 2442, "type": 24, "weight": 30.0}, {"node1": 134247, "node2": 3376, "type": 9, "weight": 25.0}, {"node1": 134247, "node2": 4146, "type": 0, "weight": 30.0}, {"node1": 134247, "node2": 4146, "type": 5, "weight": 69.0}, {"node1": 134247, "node2": 4209, "type": 64, "weight": 116.0}, {"node1": 134247, "node2": 4552, "type": 32, "weight": 7.0}, {"node1": 134247, "node2": 4979, "type": 0, "weight": 28.0}, {"node1": 134247, "node2": 6184, "type": 23, "weight": 9.0}, {"node1": 134247, "node2": 7045, "type": 0, "weight": 43.0}, {"node1": 134247, "node2": 7045, "type": 5, "weight": 79.0}, {"node1": 134247, "node2": 7045, "type": 35, "weight": 40.0}, {"node1": 134247, "node2": 7724, "type": 26, "weight": 30.0}, {"node1": 134247, "node2": 7976, "type": 0, "weight": 34.0}, {"node1": 134247, "node2": 9626, "type": 23, "weight": 35.0}, {"node1": 134247, "node2": 12037, "type": 24, "weight": 30.0}, {"node1": 134247, "node2": 13369, "type": 6, "weight": 16.0}, {"node1": 134247, "node2": 13788, "type": 0, "weight": 28.0}, {"node1": 134247, "node2": 13788, "type": 5, "weight": 56.0}, {"node1": 134247, "node2": 13883, "type": 777, "weight": 10.0}, {"node1": 134247, "node2": 14330, "type": 32, "weight": 39.0}, {"node1": 134247, "node2": 14563, "type": 0, "weight": 325.0}, {"node1": 134247, "node2": 14563, "type": 99, "weight": 40.0}, {"node1": 134247, "node2": 15196, "type": 106, "weight": 2.0}, {"node1": 134247, "node2": 15279, "type": 23, "weight": 26.0}, {"node1": 134247, "node2": 15730, "type": 0, "weight": 20.0}, {"node1": 134247, "node2": 15730, "type": 64, "weight": 151.0}, {"node1": 134247, "node2": 16110, "type": 0, "weight": 15.0}, {"node1": 134247, "node2": 16110, "type": 9, "weight": 31.0}, {"node1": 134247, "node2": 16747, "type": 9, "weight": 26.0}, {"node1": 134247, "node2": 17559, "type": 6, "weight": 27.0}, {"node1": 134247, "node2": 17927, "type": 32, "weight": 4.0}, {"node1": 134247, "node2": 18128, "type": 23, "weight": 26.0}, {"node1": 134247, "node2": 19356, "type": 0, "weight": 119.0}, {"node1": 134247, "node2": 19356, "type": 3, "weight": 28.0}, {"node1": 134247, "node2": 19452, "type": 64, "weight": 128.0}, {"node1": 134247, "node2": 20202, "type": 32, "weight": 13.0}, {"node1": 134247, "node2": 20269, "type": 17, "weight": 29.0}, {"node1": 134247, "node2": 20528, "type": 6, "weight": 16.0}, {"node1": 134247, "node2": 22218, "type": 15, "weight": 26.0}, {"node1": 134247, "node2": 22243, "type": 777, "weight": 10.0}, {"node1": 134247, "node2": 22264, "type": 32, "weight": 4.0}, {"node1": 134247, "node2": 22885, "type": 666, "weight": 5.0}, {"node1": 134247, "node2": 23114, "type": 32, "weight": 4.0}, {"node1": 134247, "node2": 24247, "type": 666, "weight": 4.0}, {"node1": 134247, "node2": 24956, "type": 0, "weight": 6.0}, {"node1": 134247, "node2": 24956, "type": 6, "weight": 56.0}, {"node1": 134247, "node2": 25260, "type": 99, "weight": 26.0}, {"node1": 134247, "node2": 25282, "type": 0, "weight": 28.0}, {"node1": 134247, "node2": 25760, "type": 0, "weight": 20.0}, {"node1": 134247, "node2": 26363, "type": 9, "weight": 26.0}, {"node1": 134247, "node2": 28453, "type": 32, "weight": 35.0}, {"node1": 134247, "node2": 29672, "type": 666, "weight": 4.0}, {"node1": 134247, "node2": 29859, "type": 32, "weight": 30.0}, {"node1": 134247, "node2": 29892, "type": 666, "weight": 3.0}, {"node1": 134247, "node2": 29892, "type": 777, "weight": 10.0}, {"node1": 134247, "node2": 30387, "type": 0, "weight": 61.0}, {"node1": 134247, "node2": 30387, "type": 666, "weight": 3.0}, {"node1": 134247, "node2": 31882, "type": 24, "weight": 30.0}, {"node1": 134247, "node2": 32735, "type": 9, "weight": 21.0}, {"node1": 134247, "node2": 33840, "type": 6, "weight": 32.0}, {"node1": 134247, "node2": 33882, "type": 24, "weight": 30.0}, {"node1": 134247, "node2": 34010, "type": 0, "weight": 20.0}, {"node1": 134247, "node2": 34898, "type": 9, "weight": 43.0}, {"node1": 134247, "node2": 35143, "type": 3, "weight": 31.0}, {"node1": 134247, "node2": 36040, "type": 0, "weight": 12.0}, {"node1": 134247, "node2": 36642, "type": 23, "weight": 26.0}, {"node1": 134247, "node2": 37298, "type": 0, "weight": 74.0}, {"node1": 134247, "node2": 37298, "type": 32, "weight": 38.0}, {"node1": 134247, "node2": 39031, "type": 9, "weight": 15.0}, {"node1": 134247, "node2": 39940, "type": 0, "weight": 32.0}, {"node1": 134247, "node2": 43253, "type": 24, "weight": 30.0}, {"node1": 134247, "node2": 43601, "type": 24, "weight": 30.0}, {"node1": 134247, "node2": 44412, "type": 0, "weight": 75.0}, {"node1": 134247, "node2": 44412, "type": 666, "weight": 60.0}, {"node1": 134247, "node2": 45671, "type": 0, "weight": 21.0}, {"node1": 134247, "node2": 46505, "type": 777, "weight": 10.0}, {"node1": 134247, "node2": 47249, "type": 64, "weight": 136.0}, {"node1": 134247, "node2": 47319, "type": 9, "weight": 15.0}, {"node1": 134247, "node2": 47918, "type": 24, "weight": 30.0}, {"node1": 134247, "node2": 49293, "type": 0, "weight": 20.0}, {"node1": 134247, "node2": 49293, "type": 6, "weight": 16.0}, {"node1": 134247, "node2": 49337, "type": 32, "weight": 4.0}, {"node1": 134247, "node2": 50081, "type": 8, "weight": 35.0}, {"node1": 134247, "node2": 53002, "type": 0, "weight": 6.0}, {"node1": 134247, "node2": 53002, "type": 3, "weight": 31.0}, {"node1": 134247, "node2": 53688, "type": 23, "weight": 7.0}, {"node1": 134247, "node2": 54794, "type": 6, "weight": 18.0}, {"node1": 134247, "node2": 55823, "type": 6, "weight": 18.0}, {"node1": 134247, "node2": 57221, "type": 32, "weight": 32.0}, {"node1": 134247, "node2": 57791, "type": 0, "weight": 271.0}, {"node1": 134247, "node2": 57933, "type": 0, "weight": 47.0}, {"node1": 134247, "node2": 59874, "type": 0, "weight": 51.0}, {"node1": 134247, "node2": 59874, "type": 5, "weight": 78.0}, {"node1": 134247, "node2": 60152, "type": 9, "weight": 29.0}, {"node1": 134247, "node2": 60835, "type": 32, "weight": 4.0}, {"node1": 134247, "node2": 61404, "type": 0, "weight": 30.0}, {"node1": 134247, "node2": 63018, "type": 666, "weight": 3.0}, {"node1": 134247, "node2": 63235, "type": 6, "weight": 18.0}, {"node1": 134247, "node2": 64238, "type": 106, "weight": 1.0}, {"node1": 134247, "node2": 65081, "type": 6, "weight": 17.0}, {"node1": 134247, "node2": 68439, "type": 0, "weight": 21.0}, {"node1": 134247, "node2": 68439, "type": 6, "weight": 52.0}, {"node1": 134247, "node2": 69283, "type": 0, "weight": 31.0}, {"node1": 134247, "node2": 69283, "type": 5, "weight": 117.0}, {"node1": 134247, "node2": 71264, "type": 0, "weight": 22.0}, {"node1": 134247, "node2": 71624, "type": 0, "weight": 3.0}, {"node1": 134247, "node2": 71624, "type": 6, "weight": 46.0}, {"node1": 134247, "node2": 72477, "type": 0, "weight": 51.0}, {"node1": 134247, "node2": 72477, "type": 6, "weight": 63.0}, {"node1": 134247, "node2": 72477, "type": 23, "weight": 28.0}, {"node1": 134247, "node2": 73890, "type": 0, "weight": 296.0}, {"node1": 134247, "node2": 73890, "type": 3, "weight": 268.0}, {"node1": 134247, "node2": 73890, "type": 35, "weight": 65.0}, {"node1": 134247, "node2": 73890, "type": 666, "weight": 7.0}, {"node1": 134247, "node2": 74846, "type": 9, "weight": 30.0}, {"node1": 134247, "node2": 74860, "type": 0, "weight": 7.0}, {"node1": 134247, "node2": 74860, "type": 6, "weight": 28.0}, {"node1": 134247, "node2": 75065, "type": 0, "weight": 45.0}, {"node1": 134247, "node2": 75065, "type": 24, "weight": 100.0}, {"node1": 134247, "node2": 77008, "type": 0, "weight": 10.0}, {"node1": 134247, "node2": 77008, "type": 9, "weight": 34.0}, {"node1": 134247, "node2": 77424, "type": 9, "weight": 27.0}, {"node1": 134247, "node2": 78119, "type": 24, "weight": 30.0}, {"node1": 134247, "node2": 78472, "type": 0, "weight": 23.0}, {"node1": 134247, "node2": 78472, "type": 5, "weight": 111.0}, {"node1": 134247, "node2": 79255, "type": 666, "weight": 4.0}, {"node1": 134247, "node2": 81680, "type": 23, "weight": 26.0}, {"node1": 134247, "node2": 81934, "type": 0, "weight": 15.0}, {"node1": 134247, "node2": 81934, "type": 9, "weight": 43.0}, {"node1": 134247, "node2": 82489, "type": 32, "weight": 4.0}, {"node1": 134247, "node2": 83944, "type": 9, "weight": 15.0}, {"node1": 134247, "node2": 85755, "type": 23, "weight": 26.0}, {"node1": 134247, "node2": 86404, "type": 0, "weight": 19.0}, {"node1": 134247, "node2": 86404, "type": 666, "weight": 7.0}, {"node1": 134247, "node2": 86640, "type": 6, "weight": 16.0}, {"node1": 134247, "node2": 87789, "type": 6, "weight": 32.0}, {"node1": 134247, "node2": 88344, "type": 23, "weight": 27.0}, {"node1": 134247, "node2": 90830, "type": 32, "weight": 4.0}, {"node1": 134247, "node2": 91691, "type": 32, "weight": 36.0}, {"node1": 134247, "node2": 91737, "type": 23, "weight": 4.0}, {"node1": 134247, "node2": 91794, "type": 6, "weight": 18.0}, {"node1": 134247, "node2": 93773, "type": 17, "weight": 30.0}, {"node1": 134247, "node2": 94431, "type": 9, "weight": 26.0}, {"node1": 134247, "node2": 95422, "type": 9, "weight": 26.0}, {"node1": 134247, "node2": 95943, "type": 0, "weight": 20.0}, {"node1": 134247, "node2": 95982, "type": 24, "weight": 30.0}, {"node1": 134247, "node2": 96211, "type": 0, "weight": 15.0}, {"node1": 134247, "node2": 96211, "type": 9, "weight": 30.0}, {"node1": 134247, "node2": 97748, "type": 0, "weight": 30.0}, {"node1": 134247, "node2": 98651, "type": 0, "weight": 22.0}, {"node1": 134247, "node2": 98651, "type": 5, "weight": 75.0}, {"node1": 134247, "node2": 99220, "type": 17, "weight": 15.0}, {"node1": 134247, "node2": 100835, "type": 777, "weight": 10.0}, {"node1": 134247, "node2": 101018, "type": 6, "weight": 22.0}, {"node1": 134247, "node2": 101172, "type": 8, "weight": 25.0}, {"node1": 134247, "node2": 101172, "type": 64, "weight": 113.0}, {"node1": 134247, "node2": 101689, "type": 6, "weight": 30.0}, {"node1": 134247, "node2": 102452, "type": 666, "weight": 7.0}, {"node1": 134247, "node2": 102499, "type": 0, "weight": 11.0}, {"node1": 134247, "node2": 102499, "type": 666, "weight": 7.0}, {"node1": 134247, "node2": 102633, "type": 0, "weight": 41.0}, {"node1": 134247, "node2": 102633, "type": 6, "weight": 25.0}, {"node1": 134247, "node2": 103311, "type": 9, "weight": 15.0}, {"node1": 134247, "node2": 103405, "type": 32, "weight": 44.0}, {"node1": 134247, "node2": 103416, "type": 6, "weight": 18.0}, {"node1": 134247, "node2": 104265, "type": 0, "weight": 28.0}, {"node1": 134247, "node2": 104265, "type": 5, "weight": 68.0}, {"node1": 134247, "node2": 104591, "type": 0, "weight": 57.0}, {"node1": 134247, "node2": 105621, "type": 17, "weight": 30.0}, {"node1": 134247, "node2": 105814, "type": 24, "weight": 30.0}, {"node1": 134247, "node2": 107477, "type": 9, "weight": 39.0}, {"node1": 134247, "node2": 108463, "type": 9, "weight": 15.0}, {"node1": 134247, "node2": 108658, "type": 8, "weight": 25.0}, {"node1": 134247, "node2": 108658, "type": 64, "weight": 169.0}, {"node1": 134247, "node2": 109785, "type": 9, "weight": 16.0}, {"node1": 134247, "node2": 110773, "type": 6, "weight": 19.0}, {"node1": 134247, "node2": 111410, "type": 0, "weight": 62.0}, {"node1": 134247, "node2": 111410, "type": 6, "weight": 57.0}, {"node1": 134247, "node2": 114327, "type": 9, "weight": 26.0}, {"node1": 134247, "node2": 115262, "type": 64, "weight": 161.0}, {"node1": 134247, "node2": 115304, "type": 6, "weight": 21.0}, {"node1": 134247, "node2": 115331, "type": 0, "weight": 21.0}, {"node1": 134247, "node2": 115331, "type": 5, "weight": 87.0}, {"node1": 134247, "node2": 115463, "type": 0, "weight": 20.0}, {"node1": 134247, "node2": 116477, "type": 0, "weight": 53.0}, {"node1": 134247, "node2": 116477, "type": 6, "weight": 57.0}, {"node1": 134247, "node2": 116546, "type": 0, "weight": 29.0}, {"node1": 134247, "node2": 117095, "type": 0, "weight": 5.0}, {"node1": 134247, "node2": 117095, "type": 3, "weight": 26.0}, {"node1": 134247, "node2": 118203, "type": 9, "weight": 25.0}, {"node1": 134247, "node2": 120157, "type": 10, "weight": 15.0}, {"node1": 134247, "node2": 120892, "type": 32, "weight": 17.0}, {"node1": 134247, "node2": 122864, "type": 0, "weight": 20.0}, {"node1": 134247, "node2": 122864, "type": 17, "weight": 26.0}, {"node1": 134247, "node2": 124600, "type": 24, "weight": 30.0}, {"node1": 134247, "node2": 126285, "type": 9, "weight": 15.0}, {"node1": 134247, "node2": 126388, "type": 9, "weight": 15.0}]}