{"nodes": {"29393": {"name": "étrenner", "type": 1, "weight": 68}, "34386": {"name": "se délaver", "type": 1, "weight": 50}, "4906": {"name": "golf", "type": 1, "weight": 997}, "2344": {"name": "mouiller", "type": 1, "weight": 728}, "24962": {"name": "cachemire", "type": 1, "weight": 116}, "27008": {"name": "évasé", "type": 1, "weight": 70}, "3219": {"name": "se fatiguer", "type": 1, "weight": 131}, "23919": {"name": "plier", "type": 1, "weight": 1125}, "1372": {"name": "chausses", "type": 1, "weight": 50}, "19108": {"name": "Mai 68", "type": 1, "weight": 135}, "5078": {"name": "pyjama", "type": 1, "weight": 294}, "10122": {"name": "jupe", "type": 1, "weight": 1070}, "21590": {"name": "nain", "type": 1, "weight": 785}, "25787": {"name": "Marlene Dietrich", "type": 1, "weight": 59}, "44397": {"name": "pantalon", "type": 1, "weight": 1833}, "18705": {"name": "gilet", "type": 1, "weight": 428}, "1384": {"name": "vivant", "type": 1, "weight": 7085}, "110": {"name": "skaï", "type": 1, "weight": 76}, "37118": {"name": "craquer", "type": 1, "weight": 288}, "28235": {"name": "blanchisserie", "type": 1, "weight": 130}, "16612": {"name": "large", "type": 1, "weight": 6280}, "33453": {"name": "mollet", "type": 1, "weight": 383}, "30617": {"name": "recouper", "type": 1, "weight": 234}, "8542": {"name": "beige", "type": 1, "weight": 170}, "19356": {"name": "sexe", "type": 1, "weight": 6819}, "6605": {"name": "instrument", "type": 1, "weight": 5772}, "10885": {"name": "fibre textile", "type": 1, "weight": 119}, "21576": {"name": "repris", "type": 1, "weight": 3284}, "26976": {"name": "vert", "type": 1, "weight": 6062}, "6527": {"name": "ourlet", "type": 1, "weight": 218}, "5390": {"name": "Wigan", "type": 1, "weight": 50}, "34042": {"name": "fabriquer", "type": 1, "weight": 4087}, "5211": {"name": "ceint", "type": 1, "weight": 58}, "10679": {"name": "Première Guerre mondiale", "type": 1, "weight": 736}, "13910": {"name": "bas", "type": 1, "weight": 11849}, "5967": {"name": "domestication", "type": 1, "weight": 237}, "151": {"name": "uniforme", "type": 1, "weight": 2707}, "20602": {"name": "kilt", "type": 1, "weight": 123}, "37163": {"name": "embarras", "type": 1, "weight": 418}, "9731": {"name": "fringues", "type": 1, "weight": 220}, "5174": {"name": "Teutons", "type": 1, "weight": 52}, "25349": {"name": "rangé", "type": 1, "weight": 161}, "37470": {"name": "taché", "type": 1, "weight": 132}, "10881": {"name": "bouton", "type": 1, "weight": 1356}, "7427": {"name": "frotter", "type": 1, "weight": 753}, "237": {"name": "objet", "type": 1, "weight": 9711}, "18699": {"name": "remonter", "type": 1, "weight": 4048}, "804": {"name": "jogging", "type": 1, "weight": 302}, "31750": {"name": "culotte", "type": 1, "weight": 511}, "34898": {"name": "pied", "type": 1, "weight": 21583}, "17186": {"name": "crêpe", "type": 1, "weight": 304}, "42": {"name": "retouche", "type": 1, "weight": 190}, "25891": {"name": "genou", "type": 1, "weight": 2789}, "15196": {"name": "blanc", "type": 1, "weight": 12871}, "7592": {"name": "ajustement", "type": 1, "weight": 1444}, "33882": {"name": "se nourrir", "type": 1, "weight": 891}, "37144": {"name": "habits", "type": 1, "weight": 383}, "12240": {"name": "Révolution française", "type": 1, "weight": 526}, "22824": {"name": "aller", "type": 1, "weight": 101317}, "11133": {"name": "toge", "type": 1, "weight": 93}, "9864": {"name": "désir", "type": 1, "weight": 9001}, "14934": {"name": "repriser", "type": 1, "weight": 1001}, "26821": {"name": "lavé", "type": 1, "weight": 259}, "2442": {"name": "vivre", "type": 1, "weight": 18756}, "3674": {"name": "botanique", "type": 1, "weight": 4173}, "14330": {"name": "satisfaction", "type": 1, "weight": 7748}, "23431": {"name": "scène", "type": 1, "weight": 10595}, "4528": {"name": "réaliser", "type": 1, "weight": 9025}, "21094": {"name": "habit", "type": 1, "weight": 1305}, "5587": {"name": "caleçon", "type": 1, "weight": 232}, "16747": {"name": "adn", "type": 1, "weight": 931}, "10962": {"name": "boutonné", "type": 1, "weight": 102}, "16110": {"name": "bouche", "type": 1, "weight": 8066}, "39149": {"name": "cuir", "type": 1, "weight": 1868}, "13451": {"name": "esprit", "type": 1, "weight": 12986}, "30044": {"name": "emprunté", "type": 1, "weight": 811}, "23481": {"name": "substantif", "type": 1, "weight": 86}, "24956": {"name": "être humain", "type": 1, "weight": 2981}, "7548": {"name": "col", "type": 1, "weight": 2557}, "33840": {"name": "primate", "type": 1, "weight": 457}, "26363": {"name": "bras", "type": 1, "weight": 11281}, "13844": {"name": "théâtre", "type": 1, "weight": 8733}, "1316": {"name": "Grèce antique", "type": 1, "weight": 353}, "11218": {"name": "leggings", "type": 1, "weight": 92}, "9755": {"name": "maillot de bain", "type": 1, "weight": 315}, "24544": {"name": "essayer", "type": 1, "weight": 7173}, "28453": {"name": "bonheur", "type": 1, "weight": 16648}, "7159": {"name": "droit", "type": 1, "weight": 25302}, "17559": {"name": "animal", "type": 1, "weight": 18949}, "20908": {"name": "braies", "type": 1, "weight": 54}, "12275": {"name": "haut-de-chausse", "type": 1, "weight": 50}, "13369": {"name": "être", "type": 1, "weight": 925580}, "34503": {"name": "pénis", "type": 1, "weight": 1314}, "27503": {"name": "retoucher", "type": 1, "weight": 185}, "3376": {"name": "membres", "type": 1, "weight": 5302}, "24170": {"name": "maculer", "type": 1, "weight": 78}, "4189": {"name": "serré", "type": 1, "weight": 220}, "12536": {"name": "macache", "type": 1, "weight": 50}, "12470": {"name": "grimpant", "type": 1, "weight": 83}, "32811": {"name": "emprunt", "type": 1, "weight": 1021}, "36250": {"name": "short", "type": 1, "weight": 364}, "30582": {"name": "jean", "type": 1, "weight": 1447}, "4363": {"name": "se donner", "type": 1, "weight": 281}, "32355": {"name": "seoir", "type": 1, "weight": 54}, "18716": {"name": "Antiquité", "type": 1, "weight": 1498}, "28988": {"name": "revers", "type": 1, "weight": 894}, "734": {"name": "Mèdes", "type": 1, "weight": 51}, "39184": {"name": "cotte", "type": 1, "weight": 63}, "452": {"name": "tympanon", "type": 1, "weight": 52}, "2773": {"name": "queue-de-morue", "type": 1, "weight": 50}, "4754": {"name": "Pygmalion", "type": 1, "weight": 64}, "8184": {"name": "sarrau", "type": 1, "weight": 74}, "19977": {"name": "ceinturon", "type": 1, "weight": 86}, "19880": {"name": "grègues", "type": 1, "weight": 51}, "24431": {"name": "se couvrir", "type": 1, "weight": 224}, "27636": {"name": "salir", "type": 1, "weight": 335}, "23654": {"name": "perdre", "type": 1, "weight": 12676}, "12060": {"name": "vêtement de travail", "type": 1, "weight": 113}, "35092": {"name": "sempiternel", "type": 1, "weight": 76}, "35069": {"name": "raccommoder", "type": 1, "weight": 80}, "8667": {"name": "Thrace", "type": 1, "weight": 176}, "5529": {"name": "Celtes", "type": 1, "weight": 1517}, "26642": {"name": "mettre en valeur", "type": 1, "weight": 207}, "34784": {"name": "Katharine Hepburn", "type": 1, "weight": 57}, "11987": {"name": "pantin", "type": 1, "weight": 102}, "33247": {"name": "revêtir", "type": 1, "weight": 448}, "23803": {"name": "ordonnance", "type": 1, "weight": 1201}, "33451": {"name": "confectionner", "type": 1, "weight": 441}, "14431": {"name": "brumaire", "type": 1, "weight": 128}, "36322": {"name": "plis", "type": 1, "weight": 113}, "24872": {"name": "polyamide", "type": 1, "weight": 96}, "4383": {"name": "luth", "type": 1, "weight": 103}, "15690": {"name": "rigolo", "type": 1, "weight": 264}, "24656": {"name": "assembler", "type": 1, "weight": 1205}, "32931": {"name": "raccourcir", "type": 1, "weight": 351}, "23999": {"name": "maculé", "type": 1, "weight": 66}, "18702": {"name": "dentier", "type": 1, "weight": 506}, "60": {"name": "bleu", "type": 1, "weight": 7392}, "35947": {"name": "habiller", "type": 1, "weight": 1489}, "7931": {"name": "accrocher", "type": 1, "weight": 1507}, "28937": {"name": "soie", "type": 1, "weight": 2418}, "20503": {"name": "multicolore", "type": 1, "weight": 124}}, "relations": [{"node1": 44397, "node2": 42, "type": 0, "weight": 30.0}, {"node1": 44397, "node2": 60, "type": 0, "weight": 30.0}, {"node1": 44397, "node2": 60, "type": 5, "weight": 65.0}, {"node1": 44397, "node2": 60, "type": 8, "weight": 101.0}, {"node1": 44397, "node2": 60, "type": 106, "weight": 3.0}, {"node1": 44397, "node2": 110, "type": 50, "weight": 28.0}, {"node1": 44397, "node2": 151, "type": 0, "weight": 89.0}, {"node1": 44397, "node2": 151, "type": 666, "weight": 68.0}, {"node1": 44397, "node2": 237, "type": 0, "weight": 65.0}, {"node1": 44397, "node2": 237, "type": 6, "weight": 75.0}, {"node1": 44397, "node2": 452, "type": 777, "weight": 9.0}, {"node1": 44397, "node2": 734, "type": 777, "weight": 8.0}, {"node1": 44397, "node2": 804, "type": 0, "weight": 18.0}, {"node1": 44397, "node2": 804, "type": 8, "weight": 101.0}, {"node1": 44397, "node2": 804, "type": 666, "weight": 5.0}, {"node1": 44397, "node2": 1316, "type": 777, "weight": 8.0}, {"node1": 44397, "node2": 1372, "type": 0, "weight": 35.0}, {"node1": 44397, "node2": 1372, "type": 777, "weight": 8.0}, {"node1": 44397, "node2": 1384, "type": 17, "weight": 36.0}, {"node1": 44397, "node2": 2344, "type": 26, "weight": 30.0}, {"node1": 44397, "node2": 2442, "type": 24, "weight": 30.0}, {"node1": 44397, "node2": 2773, "type": 0, "weight": 20.0}, {"node1": 44397, "node2": 3219, "type": 24, "weight": 30.0}, {"node1": 44397, "node2": 3376, "type": 9, "weight": 25.0}, {"node1": 44397, "node2": 3674, "type": 0, "weight": 36.0}, {"node1": 44397, "node2": 4189, "type": 0, "weight": 10.0}, {"node1": 44397, "node2": 4189, "type": 17, "weight": 60.0}, {"node1": 44397, "node2": 4363, "type": 24, "weight": 30.0}, {"node1": 44397, "node2": 4383, "type": 777, "weight": 9.0}, {"node1": 44397, "node2": 4528, "type": 38, "weight": 5.0}, {"node1": 44397, "node2": 4754, "type": 777, "weight": 8.0}, {"node1": 44397, "node2": 4906, "type": 0, "weight": 31.0}, {"node1": 44397, "node2": 5078, "type": 0, "weight": 27.0}, {"node1": 44397, "node2": 5078, "type": 10, "weight": 10.0}, {"node1": 44397, "node2": 5174, "type": 777, "weight": 8.0}, {"node1": 44397, "node2": 5211, "type": 0, "weight": 20.0}, {"node1": 44397, "node2": 5390, "type": 777, "weight": 8.0}, {"node1": 44397, "node2": 5529, "type": 777, "weight": 8.0}, {"node1": 44397, "node2": 5587, "type": 0, "weight": 26.0}, {"node1": 44397, "node2": 5587, "type": 5, "weight": 79.0}, {"node1": 44397, "node2": 5587, "type": 21, "weight": 60.0}, {"node1": 44397, "node2": 5967, "type": 777, "weight": 8.0}, {"node1": 44397, "node2": 6527, "type": 0, "weight": 4.0}, {"node1": 44397, "node2": 6527, "type": 9, "weight": 26.0}, {"node1": 44397, "node2": 6605, "type": 0, "weight": 21.0}, {"node1": 44397, "node2": 6605, "type": 6, "weight": 54.0}, {"node1": 44397, "node2": 7159, "type": 17, "weight": 34.0}, {"node1": 44397, "node2": 7427, "type": 30, "weight": 26.0}, {"node1": 44397, "node2": 7548, "type": 0, "weight": 39.0}, {"node1": 44397, "node2": 7592, "type": 153, "weight": 27.0}, {"node1": 44397, "node2": 7931, "type": 26, "weight": 30.0}, {"node1": 44397, "node2": 8184, "type": 0, "weight": 20.0}, {"node1": 44397, "node2": 8542, "type": 0, "weight": 25.0}, {"node1": 44397, "node2": 8542, "type": 106, "weight": 85.0}, {"node1": 44397, "node2": 8667, "type": 777, "weight": 8.0}, {"node1": 44397, "node2": 9731, "type": 0, "weight": 21.0}, {"node1": 44397, "node2": 9731, "type": 6, "weight": 20.0}, {"node1": 44397, "node2": 9755, "type": 21, "weight": 56.0}, {"node1": 44397, "node2": 9864, "type": 32, "weight": 33.0}, {"node1": 44397, "node2": 10122, "type": 0, "weight": 61.0}, {"node1": 44397, "node2": 10122, "type": 20, "weight": 31.0}, {"node1": 44397, "node2": 10122, "type": 21, "weight": 30.0}, {"node1": 44397, "node2": 10679, "type": 777, "weight": 8.0}, {"node1": 44397, "node2": 10881, "type": 9, "weight": 69.0}, {"node1": 44397, "node2": 10881, "type": 28, "weight": 38.0}, {"node1": 44397, "node2": 10885, "type": 0, "weight": 20.0}, {"node1": 44397, "node2": 10962, "type": 17, "weight": 34.0}, {"node1": 44397, "node2": 11133, "type": 0, "weight": 20.0}, {"node1": 44397, "node2": 11218, "type": 777, "weight": 8.0}, {"node1": 44397, "node2": 11987, "type": 0, "weight": 28.0}, {"node1": 44397, "node2": 11987, "type": 5, "weight": 66.0}, {"node1": 44397, "node2": 12060, "type": 0, "weight": 20.0}, {"node1": 44397, "node2": 12240, "type": 777, "weight": 8.0}, {"node1": 44397, "node2": 12275, "type": 0, "weight": 32.0}, {"node1": 44397, "node2": 12470, "type": 0, "weight": 28.0}, {"node1": 44397, "node2": 12470, "type": 5, "weight": 81.0}, {"node1": 44397, "node2": 12470, "type": 8, "weight": 29.0}, {"node1": 44397, "node2": 12536, "type": 0, "weight": 20.0}, {"node1": 44397, "node2": 13369, "type": 6, "weight": 25.0}, {"node1": 44397, "node2": 13451, "type": 9, "weight": 27.0}, {"node1": 44397, "node2": 13844, "type": 0, "weight": 46.0}, {"node1": 44397, "node2": 13844, "type": 35, "weight": 45.0}, {"node1": 44397, "node2": 13910, "type": 0, "weight": 4.0}, {"node1": 44397, "node2": 13910, "type": 666, "weight": 2.0}, {"node1": 44397, "node2": 14330, "type": 32, "weight": 39.0}, {"node1": 44397, "node2": 14431, "type": 777, "weight": 10.0}, {"node1": 44397, "node2": 14934, "type": 26, "weight": 100.0}, {"node1": 44397, "node2": 15196, "type": 17, "weight": 57.0}, {"node1": 44397, "node2": 15196, "type": 106, "weight": 2.0}, {"node1": 44397, "node2": 15690, "type": 0, "weight": 32.0}, {"node1": 44397, "node2": 16110, "type": 0, "weight": 24.0}, {"node1": 44397, "node2": 16110, "type": 9, "weight": 29.0}, {"node1": 44397, "node2": 16612, "type": 17, "weight": 80.0}, {"node1": 44397, "node2": 16747, "type": 9, "weight": 27.0}, {"node1": 44397, "node2": 17186, "type": 0, "weight": 30.0}, {"node1": 44397, "node2": 17559, "type": 6, "weight": 30.0}, {"node1": 44397, "node2": 18699, "type": 26, "weight": 30.0}, {"node1": 44397, "node2": 18702, "type": 0, "weight": 20.0}, {"node1": 44397, "node2": 18705, "type": 0, "weight": 45.0}, {"node1": 44397, "node2": 18716, "type": 777, "weight": 8.0}, {"node1": 44397, "node2": 19108, "type": 777, "weight": 10.0}, {"node1": 44397, "node2": 19356, "type": 9, "weight": 14.0}, {"node1": 44397, "node2": 19880, "type": 0, "weight": 24.0}, {"node1": 44397, "node2": 19880, "type": 5, "weight": 115.0}, {"node1": 44397, "node2": 19977, "type": 0, "weight": 26.0}, {"node1": 44397, "node2": 20503, "type": 0, "weight": 28.0}, {"node1": 44397, "node2": 20602, "type": 0, "weight": 34.0}, {"node1": 44397, "node2": 20908, "type": 0, "weight": 106.0}, {"node1": 44397, "node2": 20908, "type": 5, "weight": 104.0}, {"node1": 44397, "node2": 20908, "type": 666, "weight": 88.0}, {"node1": 44397, "node2": 21094, "type": 0, "weight": 96.0}, {"node1": 44397, "node2": 21094, "type": 6, "weight": 357.0}, {"node1": 44397, "node2": 21094, "type": 20, "weight": 35.0}, {"node1": 44397, "node2": 21576, "type": 17, "weight": 12.0}, {"node1": 44397, "node2": 21590, "type": 0, "weight": 32.0}, {"node1": 44397, "node2": 22824, "type": 24, "weight": 30.0}, {"node1": 44397, "node2": 23431, "type": 0, "weight": 30.0}, {"node1": 44397, "node2": 23481, "type": 777, "weight": 9.0}, {"node1": 44397, "node2": 23654, "type": 26, "weight": 30.0}, {"node1": 44397, "node2": 23803, "type": 777, "weight": 8.0}, {"node1": 44397, "node2": 23919, "type": 0, "weight": 20.0}, {"node1": 44397, "node2": 23919, "type": 26, "weight": 100.0}, {"node1": 44397, "node2": 23999, "type": 17, "weight": 26.0}, {"node1": 44397, "node2": 24170, "type": 26, "weight": 32.0}, {"node1": 44397, "node2": 24431, "type": 0, "weight": 21.0}, {"node1": 44397, "node2": 24544, "type": 0, "weight": 22.0}, {"node1": 44397, "node2": 24544, "type": 26, "weight": 100.0}, {"node1": 44397, "node2": 24656, "type": 63, "weight": 5.0}, {"node1": 44397, "node2": 24872, "type": 50, "weight": 36.0}, {"node1": 44397, "node2": 24956, "type": 0, "weight": 21.0}, {"node1": 44397, "node2": 24956, "type": 6, "weight": 53.0}, {"node1": 44397, "node2": 24962, "type": 777, "weight": 8.0}, {"node1": 44397, "node2": 25349, "type": 17, "weight": 30.0}, {"node1": 44397, "node2": 25787, "type": 777, "weight": 10.0}, {"node1": 44397, "node2": 25891, "type": 777, "weight": 8.0}, {"node1": 44397, "node2": 26363, "type": 9, "weight": 29.0}, {"node1": 44397, "node2": 26642, "type": 24, "weight": 5.0}, {"node1": 44397, "node2": 26821, "type": 17, "weight": 26.0}, {"node1": 44397, "node2": 26976, "type": 106, "weight": 1.0}, {"node1": 44397, "node2": 27008, "type": 17, "weight": 5.0}, {"node1": 44397, "node2": 27503, "type": 0, "weight": 20.0}, {"node1": 44397, "node2": 27503, "type": 26, "weight": 100.0}, {"node1": 44397, "node2": 27636, "type": 26, "weight": 30.0}, {"node1": 44397, "node2": 28235, "type": 15, "weight": 34.0}, {"node1": 44397, "node2": 28453, "type": 32, "weight": 62.0}, {"node1": 44397, "node2": 28937, "type": 0, "weight": 20.0}, {"node1": 44397, "node2": 28937, "type": 50, "weight": 35.0}, {"node1": 44397, "node2": 28988, "type": 0, "weight": 35.0}, {"node1": 44397, "node2": 28988, "type": 666, "weight": 1.0}, {"node1": 44397, "node2": 29393, "type": 26, "weight": 5.0}, {"node1": 44397, "node2": 30044, "type": 17, "weight": 35.0}, {"node1": 44397, "node2": 30582, "type": 0, "weight": 161.0}, {"node1": 44397, "node2": 30582, "type": 5, "weight": 111.0}, {"node1": 44397, "node2": 30582, "type": 8, "weight": 151.0}, {"node1": 44397, "node2": 30582, "type": 50, "weight": 45.0}, {"node1": 44397, "node2": 30582, "type": 666, "weight": 5.0}, {"node1": 44397, "node2": 30617, "type": 0, "weight": 25.0}, {"node1": 44397, "node2": 30617, "type": 26, "weight": 30.0}, {"node1": 44397, "node2": 31750, "type": 0, "weight": 41.0}, {"node1": 44397, "node2": 31750, "type": 5, "weight": 170.0}, {"node1": 44397, "node2": 31750, "type": 8, "weight": 111.0}, {"node1": 44397, "node2": 31750, "type": 21, "weight": 53.0}, {"node1": 44397, "node2": 31750, "type": 777, "weight": 8.0}, {"node1": 44397, "node2": 32355, "type": 24, "weight": 30.0}, {"node1": 44397, "node2": 32811, "type": 777, "weight": 9.0}, {"node1": 44397, "node2": 32931, "type": 0, "weight": 28.0}, {"node1": 44397, "node2": 32931, "type": 26, "weight": 30.0}, {"node1": 44397, "node2": 33247, "type": 0, "weight": 20.0}, {"node1": 44397, "node2": 33451, "type": 38, "weight": 28.0}, {"node1": 44397, "node2": 33453, "type": 28, "weight": 52.0}, {"node1": 44397, "node2": 33453, "type": 777, "weight": 8.0}, {"node1": 44397, "node2": 33840, "type": 6, "weight": 30.0}, {"node1": 44397, "node2": 33882, "type": 24, "weight": 30.0}, {"node1": 44397, "node2": 34042, "type": 38, "weight": 35.0}, {"node1": 44397, "node2": 34386, "type": 24, "weight": 30.0}, {"node1": 44397, "node2": 34503, "type": 28, "weight": 38.0}, {"node1": 44397, "node2": 34784, "type": 777, "weight": 8.0}, {"node1": 44397, "node2": 34898, "type": 9, "weight": 32.0}, {"node1": 44397, "node2": 35069, "type": 0, "weight": 29.0}, {"node1": 44397, "node2": 35069, "type": 26, "weight": 30.0}, {"node1": 44397, "node2": 35092, "type": 17, "weight": 9.0}, {"node1": 44397, "node2": 35947, "type": 0, "weight": 29.0}, {"node1": 44397, "node2": 35947, "type": 25, "weight": 32.0}, {"node1": 44397, "node2": 36250, "type": 0, "weight": 92.0}, {"node1": 44397, "node2": 36250, "type": 8, "weight": 111.0}, {"node1": 44397, "node2": 36250, "type": 21, "weight": 60.0}, {"node1": 44397, "node2": 36250, "type": 67, "weight": 27.0}, {"node1": 44397, "node2": 36250, "type": 78, "weight": 29.0}, {"node1": 44397, "node2": 36250, "type": 666, "weight": 2.0}, {"node1": 44397, "node2": 36322, "type": 0, "weight": 24.0}, {"node1": 44397, "node2": 37118, "type": 0, "weight": 24.0}, {"node1": 44397, "node2": 37144, "type": 0, "weight": 21.0}, {"node1": 44397, "node2": 37163, "type": 32, "weight": 1.0}, {"node1": 44397, "node2": 37470, "type": 17, "weight": 21.0}, {"node1": 44397, "node2": 37470, "type": 106, "weight": 626.0}, {"node1": 44397, "node2": 39149, "type": 0, "weight": 31.0}, {"node1": 44397, "node2": 39149, "type": 50, "weight": 36.0}, {"node1": 44397, "node2": 39149, "type": 666, "weight": 5.0}, {"node1": 44397, "node2": 39184, "type": 0, "weight": 21.0}, {"node1": 44397, "node2": 39184, "type": 5, "weight": 81.0}]}