{"nodes": {"15306603": {"name": "vice du consentement", "type": 1, "weight": 25}, "183557": {"name": "parti-pris", "type": 1, "weight": 66}, "65470": {"name": "atteinte", "type": 1, "weight": 2810}, "40814": {"name": "parti pris", "type": 1, "weight": 141}, "7033292": {"name": "en:prejudice", "type": 1, "weight": 25}, "112637": {"name": "lésion", "type": 1, "weight": 781}, "36738": {"name": "préjudice", "type": 1, "weight": 1433}, "319694": {"name": "processus pathologique", "type": 1, "weight": 15}, "5663": {"name": "processus", "type": 1, "weight": 11564}, "324839": {"name": "atteinte>102206", "type": 1, "weight": 60}, "15469472": {"name": "en:firm stance", "type": 1, "weight": 25}, "15469473": {"name": "en:committed stance", "type": 1, "weight": 25}, "15469474": {"name": "en:committed position", "type": 1, "weight": 25}}, "relations": [{"node1": 112637, "node2": 5663, "type": 6, "weight": 31.0}, {"node1": 112637, "node2": 36738, "type": 6, "weight": 35.0}, {"node1": 112637, "node2": 40814, "type": 6, "weight": 34.0}, {"node1": 112637, "node2": 65470, "type": 6, "weight": 182.0}, {"node1": 112637, "node2": 183557, "type": 6, "weight": 25.0}, {"node1": 112637, "node2": 319694, "type": 6, "weight": 146.0}, {"node1": 112637, "node2": 324839, "type": 6, "weight": 249.0}, {"node1": 112637, "node2": 7033292, "type": 6, "weight": 40.0}, {"node1": 112637, "node2": 15306603, "type": 6, "weight": 45.0}, {"node1": 112637, "node2": 15469472, "type": 6, "weight": 25.0}, {"node1": 112637, "node2": 15469473, "type": 6, "weight": 25.0}, {"node1": 112637, "node2": 15469474, "type": 6, "weight": 25.0}]}