{"nodes": {"96738": {"name": "argument", "type": 1, "weight": 5741}, "15443224": {"name": "en:literary device", "type": 1, "weight": 25}, "15324195": {"name": "en:rhetorical figure", "type": 1, "weight": 25}, "177408": {"name": "figure de style", "type": 1, "weight": 145}, "3891": {"name": "argumentation", "type": 1, "weight": 6089}, "8084": {"name": "figure de rhétorique", "type": 1, "weight": 67}, "5516930": {"name": "procédé littéraire", "type": 1, "weight": 31}, "57499": {"name": "trope", "type": 1, "weight": 85}, "80069": {"name": "modification", "type": 1, "weight": 8157}, "354030": {"name": "figure rhétorique", "type": 1, "weight": 50}, "77206": {"name": "ornementation", "type": 1, "weight": 110}, "112787598": {"name": "Figure de style", "type": 1, "weight": 25}, "14938377": {"name": "en:figure of speech", "type": 1, "weight": 25}, "15219689": {"name": "en:stylistic device", "type": 1, "weight": 25}}, "relations": [{"node1": 57499, "node2": 3891, "type": 6, "weight": 15.0}, {"node1": 57499, "node2": 8084, "type": 6, "weight": 15.0}, {"node1": 57499, "node2": 77206, "type": 6, "weight": 15.0}, {"node1": 57499, "node2": 80069, "type": 6, "weight": 15.0}, {"node1": 57499, "node2": 96738, "type": 6, "weight": 15.0}, {"node1": 57499, "node2": 177408, "type": 6, "weight": 88.0}, {"node1": 57499, "node2": 354030, "type": 6, "weight": 10.0}, {"node1": 57499, "node2": 5516930, "type": 6, "weight": 25.0}, {"node1": 57499, "node2": 14938377, "type": 6, "weight": 27.0}, {"node1": 57499, "node2": 15219689, "type": 6, "weight": 36.0}, {"node1": 57499, "node2": 15324195, "type": 6, "weight": 35.0}, {"node1": 57499, "node2": 15443224, "type": 6, "weight": 27.0}, {"node1": 57499, "node2": 112787598, "type": 6, "weight": 34.0}]}