{"nodes": {"27860": {"name": "logarithmes", "type": 1, "weight": 50}, "44889": {"name": "Python", "type": 1, "weight": 1596}, "18060": {"name": "pitonner", "type": 1, "weight": 52}, "39764": {"name": "registre", "type": 1, "weight": 2961}, "7780": {"name": "sportif", "type": 1, "weight": 3069}, "69988": {"name": "développeur", "type": 1, "weight": 409}, "32249": {"name": "épinette", "type": 1, "weight": 73}, "1384": {"name": "vivant", "type": 1, "weight": 7084}, "14363": {"name": "saisie", "type": 1, "weight": 568}, "26880": {"name": "violoncelle", "type": 1, "weight": 1410}, "10034": {"name": "2e", "type": 1, "weight": 196}, "37118": {"name": "craquer", "type": 1, "weight": 288}, "4748": {"name": "cédille", "type": 1, "weight": 54}, "38448": {"name": "dysfonctionnement", "type": 1, "weight": 580}, "25638": {"name": "compact", "type": 1, "weight": 1727}, "13115": {"name": "mâchoire", "type": 1, "weight": 612}, "8542": {"name": "beige", "type": 1, "weight": 170}, "31477": {"name": "sténotype", "type": 1, "weight": 50}, "52660": {"name": "clé", "type": 1, "weight": 4240}, "6605": {"name": "instrument", "type": 1, "weight": 5772}, "50195": {"name": "piano", "type": 1, "weight": 3509}, "5319": {"name": "musical", "type": 1, "weight": 3718}, "39525": {"name": "chatter", "type": 1, "weight": 175}, "54071": {"name": "hypertexte", "type": 1, "weight": 118}, "34315": {"name": "pianoter", "type": 1, "weight": 201}, "61973": {"name": "virginal", "type": 1, "weight": 63}, "32719": {"name": "réactif", "type": 1, "weight": 326}, "8595": {"name": "corde", "type": 1, "weight": 3433}, "10881": {"name": "bouton", "type": 1, "weight": 1356}, "35861": {"name": "dépression", "type": 1, "weight": 3546}, "69820": {"name": "piano-forte", "type": 1, "weight": 50}, "11467": {"name": "américain", "type": 1, "weight": 6795}, "53730": {"name": "majuscule", "type": 1, "weight": 2227}, "59893": {"name": "entrée", "type": 1, "weight": 6339}, "237": {"name": "objet", "type": 1, "weight": 9711}, "61568": {"name": "harmonium", "type": 1, "weight": 66}, "2959": {"name": "saleté", "type": 1, "weight": 823}, "16568": {"name": "mise en mouvement", "type": 1, "weight": 58}, "58768": {"name": "organisme", "type": 1, "weight": 5273}, "150": {"name": "chat", "type": 1, "weight": 7400}, "63831": {"name": "taper", "type": 1, "weight": 1647}, "12363": {"name": "utilisateur", "type": 1, "weight": 6672}, "22264": {"name": "colère", "type": 1, "weight": 6009}, "34898": {"name": "pied", "type": 1, "weight": 21583}, "32348": {"name": "informaticien", "type": 1, "weight": 486}, "63897": {"name": "machine à écrire", "type": 1, "weight": 227}, "43167": {"name": "programmeur", "type": 1, "weight": 94}, "29859": {"name": "mal-être", "type": 1, "weight": 443}, "64238": {"name": "noir", "type": 1, "weight": 13771}, "36134": {"name": "déboîter", "type": 1, "weight": 71}, "15196": {"name": "blanc", "type": 1, "weight": 12871}, "54234": {"name": "écriture", "type": 1, "weight": 6510}, "62611": {"name": "utiliser", "type": 1, "weight": 18343}, "67368": {"name": "mécanique", "type": 1, "weight": 4693}, "30030": {"name": "entreprise", "type": 1, "weight": 9570}, "70283": {"name": "travail", "type": 1, "weight": 27618}, "42519": {"name": "ergonomie", "type": 1, "weight": 1009}, "56929": {"name": "programmation", "type": 1, "weight": 4965}, "49207": {"name": "acteur", "type": 1, "weight": 9623}, "65064": {"name": "ensemble", "type": 1, "weight": 14004}, "23705": {"name": "productivité", "type": 1, "weight": 2528}, "14429": {"name": "connectivité", "type": 1, "weight": 2077}, "48135": {"name": "application", "type": 1, "weight": 10918}, "53314": {"name": "jeu", "type": 1, "weight": 12266}, "51528": {"name": "son", "type": 1, "weight": 370438}, "117739": {"name": "clavier", "type": 1, "weight": 3533}, "34954": {"name": "frapper", "type": 1, "weight": 6306}, "59993": {"name": "réalisateur", "type": 1, "weight": 5382}, "34065": {"name": "Marin Mersenne", "type": 1, "weight": 81}, "16110": {"name": "bouche", "type": 1, "weight": 8066}, "12105": {"name": "communication", "type": 1, "weight": 42318}, "5425": {"name": "machine", "type": 1, "weight": 8017}, "45179": {"name": "maison", "type": 1, "weight": 38478}, "30821": {"name": "doigts", "type": 1, "weight": 2691}, "34425": {"name": "numérique", "type": 1, "weight": 8677}, "28453": {"name": "bonheur", "type": 1, "weight": 16648}, "57221": {"name": "joie", "type": 1, "weight": 14508}, "13701": {"name": "technique", "type": 1, "weight": 10722}, "66372": {"name": "texte", "type": 1, "weight": 16553}, "31057": {"name": "techniques", "type": 1, "weight": 6122}, "46742": {"name": "logiciel", "type": 1, "weight": 6593}, "55621": {"name": "pédalier", "type": 1, "weight": 146}, "54899": {"name": "réunion", "type": 1, "weight": 5108}, "18434": {"name": "hurdy-gurdy", "type": 1, "weight": 50}, "37298": {"name": "amour", "type": 1, "weight": 33666}, "43253": {"name": "dormir", "type": 1, "weight": 10614}, "38361": {"name": "miette", "type": 1, "weight": 322}, "59696": {"name": "rancoeur", "type": 1, "weight": 171}, "62406": {"name": "dactylo", "type": 1, "weight": 130}, "58386": {"name": "programmer", "type": 1, "weight": 695}, "34248": {"name": "frappé", "type": 1, "weight": 910}, "25899": {"name": "pianoforte", "type": 1, "weight": 51}, "52443": {"name": "orgue", "type": 1, "weight": 1340}, "4111": {"name": "toccata", "type": 1, "weight": 50}, "13927": {"name": "ébène", "type": 1, "weight": 106}, "31814": {"name": "répétitivité", "type": 1, "weight": 61}, "33574": {"name": "calculette", "type": 1, "weight": 269}, "62706": {"name": "doigt", "type": 1, "weight": 5668}, "62028": {"name": "instruments à clavier", "type": 1, "weight": 51}, "48866": {"name": "accordéon", "type": 1, "weight": 210}, "43816": {"name": "calculatrices", "type": 1, "weight": 69}, "15559": {"name": "Octave", "type": 1, "weight": 168}, "44657": {"name": "tapoter", "type": 1, "weight": 106}, "68977": {"name": "saisi", "type": 1, "weight": 319}, "61936": {"name": "ennui", "type": 1, "weight": 1975}, "68269": {"name": "xylophone", "type": 1, "weight": 116}, "26970": {"name": "écran", "type": 1, "weight": 4731}, "4865": {"name": "portée", "type": 1, "weight": 4093}, "53833": {"name": "peausserie", "type": 1, "weight": 70}, "61294": {"name": "sous-clavier", "type": 1, "weight": 50}, "34821": {"name": "positif", "type": 1, "weight": 3345}, "40368": {"name": "mulot", "type": 1, "weight": 293}, "60607": {"name": "métonymie", "type": 1, "weight": 97}, "52934": {"name": "commande", "type": 1, "weight": 3735}, "68976": {"name": "instruments de musique", "type": 1, "weight": 139}, "35759": {"name": "configurer", "type": 1, "weight": 175}, "29839": {"name": "connecteur", "type": 1, "weight": 146}, "50889": {"name": "gris", "type": 1, "weight": 4826}, "41501": {"name": "marqueterie", "type": 1, "weight": 61}, "9548": {"name": "virtuel", "type": 1, "weight": 929}, "35989": {"name": "reprogrammer", "type": 1, "weight": 111}, "45297": {"name": "boîtier", "type": 1, "weight": 95}, "65951": {"name": "pianiste", "type": 1, "weight": 2421}, "9462": {"name": "pouce", "type": 1, "weight": 1523}, "11098": {"name": "Mac", "type": 1, "weight": 3094}, "1815": {"name": "mono", "type": 1, "weight": 83}, "8254": {"name": "bureau", "type": 1, "weight": 6149}, "28758": {"name": "ergonomique", "type": 1, "weight": 90}, "39401": {"name": "synthétiseur", "type": 1, "weight": 170}, "2463": {"name": "ordinateur portable", "type": 1, "weight": 136}, "46534": {"name": "tactile", "type": 1, "weight": 186}, "60748": {"name": "dysfonctionner", "type": 1, "weight": 104}, "989": {"name": "chromatisme", "type": 1, "weight": 54}, "21087": {"name": "notes", "type": 1, "weight": 3825}, "17685": {"name": "poussière", "type": 1, "weight": 2636}, "3194": {"name": "micro-ordinateur", "type": 1, "weight": 78}, "21764": {"name": "curseur", "type": 1, "weight": 126}}, "relations": [{"node1": 117739, "node2": 150, "type": 0, "weight": 21.0}, {"node1": 117739, "node2": 150, "type": 28, "weight": 30.0}, {"node1": 117739, "node2": 237, "type": 0, "weight": 31.0}, {"node1": 117739, "node2": 237, "type": 6, "weight": 157.0}, {"node1": 117739, "node2": 989, "type": 0, "weight": 20.0}, {"node1": 117739, "node2": 1384, "type": 17, "weight": 25.0}, {"node1": 117739, "node2": 1815, "type": 0, "weight": 20.0}, {"node1": 117739, "node2": 2463, "type": 0, "weight": 10.0}, {"node1": 117739, "node2": 2463, "type": 10, "weight": 53.0}, {"node1": 117739, "node2": 2959, "type": 28, "weight": 31.0}, {"node1": 117739, "node2": 3194, "type": 0, "weight": 30.0}, {"node1": 117739, "node2": 3194, "type": 10, "weight": 41.0}, {"node1": 117739, "node2": 4111, "type": 0, "weight": 27.0}, {"node1": 117739, "node2": 4748, "type": 0, "weight": 20.0}, {"node1": 117739, "node2": 4865, "type": 0, "weight": 30.0}, {"node1": 117739, "node2": 4865, "type": 5, "weight": 66.0}, {"node1": 117739, "node2": 5319, "type": 17, "weight": 53.0}, {"node1": 117739, "node2": 5425, "type": 0, "weight": 10.0}, {"node1": 117739, "node2": 5425, "type": 10, "weight": 80.0}, {"node1": 117739, "node2": 6605, "type": 0, "weight": 78.0}, {"node1": 117739, "node2": 6605, "type": 35, "weight": 50.0}, {"node1": 117739, "node2": 7780, "type": 777, "weight": 6.0}, {"node1": 117739, "node2": 8254, "type": 15, "weight": 166.0}, {"node1": 117739, "node2": 8254, "type": 666, "weight": 3.0}, {"node1": 117739, "node2": 8542, "type": 106, "weight": 1.0}, {"node1": 117739, "node2": 8595, "type": 0, "weight": 12.0}, {"node1": 117739, "node2": 9462, "type": 666, "weight": 3.0}, {"node1": 117739, "node2": 9548, "type": 777, "weight": 7.0}, {"node1": 117739, "node2": 10034, "type": 17, "weight": 33.0}, {"node1": 117739, "node2": 10881, "type": 9, "weight": 10.0}, {"node1": 117739, "node2": 11098, "type": 0, "weight": 29.0}, {"node1": 117739, "node2": 11467, "type": 17, "weight": 26.0}, {"node1": 117739, "node2": 12105, "type": 41, "weight": 27.0}, {"node1": 117739, "node2": 12363, "type": 122, "weight": 31.0}, {"node1": 117739, "node2": 12363, "type": 156, "weight": 46.0}, {"node1": 117739, "node2": 13115, "type": 0, "weight": 29.0}, {"node1": 117739, "node2": 13115, "type": 5, "weight": 70.0}, {"node1": 117739, "node2": 13701, "type": 0, "weight": 35.0}, {"node1": 117739, "node2": 13701, "type": 3, "weight": 35.0}, {"node1": 117739, "node2": 13927, "type": 777, "weight": 10.0}, {"node1": 117739, "node2": 14363, "type": 137, "weight": 29.0}, {"node1": 117739, "node2": 14363, "type": 139, "weight": 41.0}, {"node1": 117739, "node2": 14363, "type": 666, "weight": 5.0}, {"node1": 117739, "node2": 14429, "type": 666, "weight": 2.0}, {"node1": 117739, "node2": 15196, "type": 106, "weight": 1.0}, {"node1": 117739, "node2": 15559, "type": 777, "weight": 7.0}, {"node1": 117739, "node2": 16110, "type": 9, "weight": 25.0}, {"node1": 117739, "node2": 16568, "type": 0, "weight": 14.0}, {"node1": 117739, "node2": 17685, "type": 28, "weight": 31.0}, {"node1": 117739, "node2": 18060, "type": 0, "weight": 25.0}, {"node1": 117739, "node2": 18434, "type": 0, "weight": 20.0}, {"node1": 117739, "node2": 18434, "type": 10, "weight": 24.0}, {"node1": 117739, "node2": 21087, "type": 0, "weight": 26.0}, {"node1": 117739, "node2": 21764, "type": 0, "weight": 20.0}, {"node1": 117739, "node2": 22264, "type": 32, "weight": 61.0}, {"node1": 117739, "node2": 23705, "type": 134, "weight": 31.0}, {"node1": 117739, "node2": 25638, "type": 17, "weight": 27.0}, {"node1": 117739, "node2": 25899, "type": 0, "weight": 30.0}, {"node1": 117739, "node2": 26880, "type": 777, "weight": 7.0}, {"node1": 117739, "node2": 26970, "type": 0, "weight": 187.0}, {"node1": 117739, "node2": 26970, "type": 75, "weight": 27.0}, {"node1": 117739, "node2": 26970, "type": 82, "weight": 25.0}, {"node1": 117739, "node2": 26970, "type": 666, "weight": 27.0}, {"node1": 117739, "node2": 27860, "type": 777, "weight": 10.0}, {"node1": 117739, "node2": 28453, "type": 32, "weight": 61.0}, {"node1": 117739, "node2": 28758, "type": 17, "weight": 40.0}, {"node1": 117739, "node2": 29839, "type": 666, "weight": 2.0}, {"node1": 117739, "node2": 29859, "type": 32, "weight": 30.0}, {"node1": 117739, "node2": 30030, "type": 15, "weight": 1.0}, {"node1": 117739, "node2": 30030, "type": 122, "weight": 25.0}, {"node1": 117739, "node2": 30821, "type": 82, "weight": 27.0}, {"node1": 117739, "node2": 31057, "type": 777, "weight": 10.0}, {"node1": 117739, "node2": 31477, "type": 8, "weight": 27.0}, {"node1": 117739, "node2": 31814, "type": 32, "weight": 61.0}, {"node1": 117739, "node2": 32249, "type": 0, "weight": 40.0}, {"node1": 117739, "node2": 32249, "type": 10, "weight": 60.0}, {"node1": 117739, "node2": 32249, "type": 666, "weight": 1.0}, {"node1": 117739, "node2": 32348, "type": 156, "weight": 35.0}, {"node1": 117739, "node2": 32719, "type": 17, "weight": 28.0}, {"node1": 117739, "node2": 33574, "type": 8, "weight": 71.0}, {"node1": 117739, "node2": 34065, "type": 777, "weight": 7.0}, {"node1": 117739, "node2": 34248, "type": 17, "weight": 25.0}, {"node1": 117739, "node2": 34315, "type": 25, "weight": 34.0}, {"node1": 117739, "node2": 34425, "type": 17, "weight": 72.0}, {"node1": 117739, "node2": 34425, "type": 666, "weight": 3.0}, {"node1": 117739, "node2": 34821, "type": 0, "weight": 20.0}, {"node1": 117739, "node2": 34898, "type": 9, "weight": 25.0}, {"node1": 117739, "node2": 34954, "type": 0, "weight": 13.0}, {"node1": 117739, "node2": 34954, "type": 25, "weight": 23.0}, {"node1": 117739, "node2": 34954, "type": 26, "weight": 27.0}, {"node1": 117739, "node2": 35759, "type": 26, "weight": 30.0}, {"node1": 117739, "node2": 35861, "type": 32, "weight": 51.0}, {"node1": 117739, "node2": 35989, "type": 25, "weight": 28.0}, {"node1": 117739, "node2": 36134, "type": 0, "weight": 20.0}, {"node1": 117739, "node2": 37118, "type": 24, "weight": 30.0}, {"node1": 117739, "node2": 37298, "type": 32, "weight": 61.0}, {"node1": 117739, "node2": 38361, "type": 28, "weight": 31.0}, {"node1": 117739, "node2": 38448, "type": 108, "weight": 25.0}, {"node1": 117739, "node2": 39401, "type": 0, "weight": 143.0}, {"node1": 117739, "node2": 39401, "type": 10, "weight": 55.0}, {"node1": 117739, "node2": 39401, "type": 82, "weight": 25.0}, {"node1": 117739, "node2": 39401, "type": 666, "weight": 65.0}, {"node1": 117739, "node2": 39525, "type": 0, "weight": 26.0}, {"node1": 117739, "node2": 39764, "type": 0, "weight": 21.0}, {"node1": 117739, "node2": 39764, "type": 5, "weight": 7.0}, {"node1": 117739, "node2": 40368, "type": 0, "weight": 29.0}, {"node1": 117739, "node2": 41501, "type": 777, "weight": 7.0}, {"node1": 117739, "node2": 42519, "type": 666, "weight": 8.0}, {"node1": 117739, "node2": 43167, "type": 82, "weight": 32.0}, {"node1": 117739, "node2": 43167, "type": 156, "weight": 46.0}, {"node1": 117739, "node2": 43253, "type": 24, "weight": 25.0}, {"node1": 117739, "node2": 43816, "type": 777, "weight": 9.0}, {"node1": 117739, "node2": 44657, "type": 26, "weight": 30.0}, {"node1": 117739, "node2": 44889, "type": 777, "weight": 10.0}, {"node1": 117739, "node2": 45179, "type": 15, "weight": 78.0}, {"node1": 117739, "node2": 45297, "type": 9, "weight": 31.0}, {"node1": 117739, "node2": 46534, "type": 17, "weight": 31.0}, {"node1": 117739, "node2": 46534, "type": 666, "weight": 2.0}, {"node1": 117739, "node2": 46534, "type": 777, "weight": 10.0}, {"node1": 117739, "node2": 46742, "type": 82, "weight": 25.0}, {"node1": 117739, "node2": 46742, "type": 155, "weight": 25.0}, {"node1": 117739, "node2": 46742, "type": 666, "weight": 2.0}, {"node1": 117739, "node2": 48135, "type": 666, "weight": 2.0}, {"node1": 117739, "node2": 48866, "type": 0, "weight": 23.0}, {"node1": 117739, "node2": 48866, "type": 10, "weight": 55.0}, {"node1": 117739, "node2": 49207, "type": 777, "weight": 6.0}, {"node1": 117739, "node2": 50195, "type": 0, "weight": 463.0}, {"node1": 117739, "node2": 50195, "type": 8, "weight": 101.0}, {"node1": 117739, "node2": 50195, "type": 10, "weight": 220.0}, {"node1": 117739, "node2": 50195, "type": 15, "weight": 128.0}, {"node1": 117739, "node2": 50195, "type": 20, "weight": 26.0}, {"node1": 117739, "node2": 50195, "type": 666, "weight": 2.0}, {"node1": 117739, "node2": 50889, "type": 106, "weight": 1.0}, {"node1": 117739, "node2": 51528, "type": 777, "weight": 7.0}, {"node1": 117739, "node2": 52443, "type": 0, "weight": 194.0}, {"node1": 117739, "node2": 52443, "type": 8, "weight": 101.0}, {"node1": 117739, "node2": 52443, "type": 10, "weight": 93.0}, {"node1": 117739, "node2": 52443, "type": 15, "weight": 88.0}, {"node1": 117739, "node2": 52443, "type": 666, "weight": 74.0}, {"node1": 117739, "node2": 52660, "type": 99, "weight": 33.0}, {"node1": 117739, "node2": 52934, "type": 0, "weight": 134.0}, {"node1": 117739, "node2": 52934, "type": 666, "weight": 118.0}, {"node1": 117739, "node2": 53314, "type": 666, "weight": 28.0}, {"node1": 117739, "node2": 53730, "type": 0, "weight": 20.0}, {"node1": 117739, "node2": 53833, "type": 0, "weight": 32.0}, {"node1": 117739, "node2": 53833, "type": 3, "weight": 29.0}, {"node1": 117739, "node2": 54071, "type": 0, "weight": 20.0}, {"node1": 117739, "node2": 54234, "type": 0, "weight": 33.0}, {"node1": 117739, "node2": 54234, "type": 666, "weight": 3.0}, {"node1": 117739, "node2": 54899, "type": 49, "weight": 25.0}, {"node1": 117739, "node2": 55621, "type": 8, "weight": 3.0}, {"node1": 117739, "node2": 56929, "type": 666, "weight": 26.0}, {"node1": 117739, "node2": 57221, "type": 32, "weight": 76.0}, {"node1": 117739, "node2": 58386, "type": 0, "weight": 96.0}, {"node1": 117739, "node2": 58386, "type": 666, "weight": 81.0}, {"node1": 117739, "node2": 58768, "type": 0, "weight": 14.0}, {"node1": 117739, "node2": 59696, "type": 32, "weight": 3.0}, {"node1": 117739, "node2": 59893, "type": 0, "weight": 26.0}, {"node1": 117739, "node2": 59893, "type": 9, "weight": 60.0}, {"node1": 117739, "node2": 59893, "type": 666, "weight": 3.0}, {"node1": 117739, "node2": 59993, "type": 777, "weight": 6.0}, {"node1": 117739, "node2": 60607, "type": 777, "weight": 6.0}, {"node1": 117739, "node2": 60748, "type": 24, "weight": 31.0}, {"node1": 117739, "node2": 61294, "type": 0, "weight": 21.0}, {"node1": 117739, "node2": 61294, "type": 11, "weight": 121.0}, {"node1": 117739, "node2": 61568, "type": 0, "weight": 20.0}, {"node1": 117739, "node2": 61568, "type": 777, "weight": 7.0}, {"node1": 117739, "node2": 61936, "type": 32, "weight": 71.0}, {"node1": 117739, "node2": 61973, "type": 0, "weight": 30.0}, {"node1": 117739, "node2": 61973, "type": 777, "weight": 7.0}, {"node1": 117739, "node2": 62028, "type": 0, "weight": 26.0}, {"node1": 117739, "node2": 62028, "type": 11, "weight": 161.0}, {"node1": 117739, "node2": 62406, "type": 0, "weight": 26.0}, {"node1": 117739, "node2": 62611, "type": 26, "weight": 30.0}, {"node1": 117739, "node2": 62706, "type": 0, "weight": 30.0}, {"node1": 117739, "node2": 62706, "type": 666, "weight": 1.0}, {"node1": 117739, "node2": 63831, "type": 0, "weight": 171.0}, {"node1": 117739, "node2": 63831, "type": 24, "weight": 30.0}, {"node1": 117739, "node2": 63831, "type": 25, "weight": 60.0}, {"node1": 117739, "node2": 63831, "type": 42, "weight": 56.0}, {"node1": 117739, "node2": 63897, "type": 0, "weight": 185.0}, {"node1": 117739, "node2": 63897, "type": 10, "weight": 53.0}, {"node1": 117739, "node2": 63897, "type": 35, "weight": 42.0}, {"node1": 117739, "node2": 63897, "type": 666, "weight": 68.0}, {"node1": 117739, "node2": 64238, "type": 106, "weight": 1.0}, {"node1": 117739, "node2": 65064, "type": 0, "weight": 21.0}, {"node1": 117739, "node2": 65064, "type": 5, "weight": 59.0}, {"node1": 117739, "node2": 65951, "type": 156, "weight": 32.0}, {"node1": 117739, "node2": 66372, "type": 0, "weight": 69.0}, {"node1": 117739, "node2": 66372, "type": 82, "weight": 31.0}, {"node1": 117739, "node2": 66372, "type": 666, "weight": 7.0}, {"node1": 117739, "node2": 67368, "type": 17, "weight": 29.0}, {"node1": 117739, "node2": 68269, "type": 777, "weight": 7.0}, {"node1": 117739, "node2": 68976, "type": 0, "weight": 30.0}, {"node1": 117739, "node2": 68977, "type": 0, "weight": 30.0}, {"node1": 117739, "node2": 69820, "type": 0, "weight": 25.0}, {"node1": 117739, "node2": 69820, "type": 777, "weight": 7.0}, {"node1": 117739, "node2": 69988, "type": 156, "weight": 51.0}, {"node1": 117739, "node2": 70283, "type": 0, "weight": 33.0}, {"node1": 117739, "node2": 70283, "type": 49, "weight": 25.0}]}