{"nodes": {"151553": {"name": "_FL:0", "type": 6, "weight": 50}, "222078": {"name": "pavé>256609>20564", "type": 1, "weight": 58}, "1560791": {"name": ":r3075145", "type": 10, "weight": 0}, "1560792": {"name": ":r1777244", "type": 10, "weight": 0}, "2578913": {"name": "Tournedos", "type": 1, "weight": 27}, "119873": {"name": "vitamines", "type": 1, "weight": 611}, "139597": {"name": "poivre", "type": 1, "weight": 827}, "168792": {"name": "choron", "type": 1, "weight": 50}, "405513": {"name": "Boeuf", "type": 1, "weight": 54}, "22772": {"name": "romsteck", "type": 1, "weight": 50}, "140377": {"name": "beurre", "type": 1, "weight": 3059}, "156387": {"name": "cuisine française", "type": 1, "weight": 200}, "42188": {"name": "filet", "type": 1, "weight": 993}, "228897": {"name": "viande bovine", "type": 1, "weight": 258}, "82147": {"name": "rond", "type": 1, "weight": 2213}, "438949": {"name": "_INFO-POLYMORPHIC", "type": 36, "weight": 50}, "422605": {"name": "hubert", "type": 1, "weight": 106}, "135982": {"name": "persil", "type": 1, "weight": 367}, "141518": {"name": "Chateaubriand", "type": 1, "weight": 67}, "317327": {"name": "_POLIT_6FN", "type": 36, "weight": 50}, "1972669": {"name": "pavé>16601", "type": 1, "weight": 5}, "205835": {"name": "poivre vert", "type": 1, "weight": 58}, "153997": {"name": "repas de Noël", "type": 1, "weight": 137}, "428313": {"name": "Foie", "type": 1, "weight": 50}, "19636": {"name": "rôti", "type": 1, "weight": 425}, "1972667": {"name": "pavé>141687", "type": 1, "weight": 25}, "174932": {"name": "Commune", "type": 1, "weight": 3116}, "317326": {"name": "_POLIT_5UMP", "type": 36, "weight": 50}, "120188": {"name": "recette", "type": 1, "weight": 3288}, "105441": {"name": "pavé", "type": 1, "weight": 628}, "215037": {"name": "boeuf>140100", "type": 1, "weight": 484}, "41642": {"name": "échalote", "type": 1, "weight": 121}, "97682": {"name": "saignant", "type": 1, "weight": 165}, "127547": {"name": "grillade", "type": 1, "weight": 585}, "156049": {"name": "repas d'affaires", "type": 1, "weight": 68}, "56362": {"name": "gras", "type": 1, "weight": 3064}, "86356": {"name": "rouge", "type": 1, "weight": 10902}, "123307": {"name": "oignon", "type": 1, "weight": 691}, "1912917": {"name": "_INFO-COUNTABLE-YES", "type": 36, "weight": 10}, "8485": {"name": "champignons", "type": 1, "weight": 3136}, "60056": {"name": "cuisson", "type": 1, "weight": 2699}, "108827": {"name": "protéines", "type": 1, "weight": 3430}, "36327": {"name": "plat", "type": 1, "weight": 5139}, "140100": {"name": "viande", "type": 1, "weight": 7236}, "166491": {"name": "filet de boeuf", "type": 1, "weight": 116}, "113902": {"name": "alimentation", "type": 1, "weight": 7475}, "79954": {"name": "restaurant", "type": 1, "weight": 6295}, "33634": {"name": "préparation", "type": 1, "weight": 7194}, "14330": {"name": "satisfaction", "type": 1, "weight": 7748}, "22605": {"name": "accompagnement", "type": 1, "weight": 5702}, "73091": {"name": "Hubert", "type": 1, "weight": 2108}, "163988": {"name": "crème fraîche", "type": 1, "weight": 229}, "55834": {"name": "commun", "type": 1, "weight": 6983}, "256015": {"name": "cuisine traditionnelle", "type": 1, "weight": 117}, "41595": {"name": "gourmet", "type": 1, "weight": 263}, "13260": {"name": "sel", "type": 1, "weight": 3175}, "89926": {"name": "chef", "type": 1, "weight": 10001}, "141899": {"name": "grillé", "type": 1, "weight": 203}, "222082": {"name": "pavé>142787", "type": 1, "weight": 104}, "74736": {"name": "repas", "type": 1, "weight": 6572}, "146885": {"name": "Nom:Mas+SG", "type": 4, "weight": 50}, "158591": {"name": "pommes de terre", "type": 1, "weight": 605}, "91657": {"name": "nutrition", "type": 1, "weight": 2956}, "47669": {"name": "sauté", "type": 1, "weight": 113}, "124092": {"name": "fer", "type": 1, "weight": 6770}, "96256": {"name": "bois", "type": 1, "weight": 11126}, "16033": {"name": "cuisine", "type": 1, "weight": 16673}, "91691": {"name": "surprise", "type": 1, "weight": 3439}, "28453": {"name": "bonheur", "type": 1, "weight": 16648}, "130164": {"name": "manger", "type": 1, "weight": 17775}, "93731": {"name": "Rossini", "type": 1, "weight": 84}, "77419": {"name": "minéraux", "type": 1, "weight": 2838}, "146357": {"name": "envie", "type": 1, "weight": 4966}, "27715": {"name": "bordelaise", "type": 1, "weight": 62}, "146887": {"name": "Nom:Mas+PL", "type": 4, "weight": 50}, "47417": {"name": "boeuf", "type": 1, "weight": 1703}, "43125": {"name": "gastronomie", "type": 1, "weight": 6038}, "239128": {"name": "_COM", "type": 36, "weight": 60}, "171870": {"name": "Nom:", "type": 4, "weight": 50}, "214275": {"name": "cuisine>143757", "type": 1, "weight": 2212}, "80199": {"name": "cuisiner", "type": 1, "weight": 2460}, "138954": {"name": "huile d'olive", "type": 1, "weight": 780}, "26979": {"name": "ail", "type": 1, "weight": 872}, "156863": {"name": "plat principal", "type": 1, "weight": 251}, "2352229": {"name": "rossini", "type": 1, "weight": 30}, "168216": {"name": "bœuf", "type": 1, "weight": 1065}, "260477": {"name": "rumsteak", "type": 1, "weight": 6}, "218746": {"name": "boucherie>140100", "type": 1, "weight": 196}, "22365": {"name": "chateaubriand", "type": 1, "weight": 51}, "49508": {"name": "châteaubriant", "type": 1, "weight": 55}, "64441": {"name": "poivrade", "type": 1, "weight": 50}, "114701": {"name": "rumsteck", "type": 1, "weight": 57}, "155774": {"name": "repas de mariage", "type": 1, "weight": 78}, "177215": {"name": "chateaubriant", "type": 1, "weight": 50}, "222081": {"name": "pavé>1972666", "type": 1, "weight": 74}, "223172": {"name": "_POL-NEG", "type": 36, "weight": 50}, "223173": {"name": "_POL-POS", "type": 36, "weight": 50}, "225881": {"name": "rond>88274", "type": 1, "weight": 28}, "235350": {"name": "bavette d'aloyau", "type": 1, "weight": 4}, "235993": {"name": "pièce du boucher", "type": 1, "weight": 52}, "241794": {"name": "_POL-NEUTRE", "type": 36, "weight": 50}, "13890": {"name": "à point", "type": 1, "weight": 1051}, "250629": {"name": "romsteak", "type": 1, "weight": 50}, "251158": {"name": "tranche de viande", "type": 1, "weight": 17}, "254876": {"name": "_POL-POS_PC", "type": 36, "weight": 50}, "254877": {"name": "_POL-NEUTRE_PC", "type": 36, "weight": 50}, "276096": {"name": "_INFO-WIKI-YES", "type": 36, "weight": 50}, "317329": {"name": "_POLIT_7NOPOL", "type": 36, "weight": 50}, "317322": {"name": "_POLIT_1ECO", "type": 36, "weight": 50}, "317323": {"name": "_POLIT_2PG", "type": 36, "weight": 50}, "317325": {"name": "_POLIT_4MD", "type": 36, "weight": 50}, "317324": {"name": "_POLIT_3PS", "type": 36, "weight": 50}, "153902": {"name": "viande de boeuf", "type": 1, "weight": 508}, "15763": {"name": "assaisonnement", "type": 1, "weight": 529}, "390709": {"name": "rumsteack", "type": 1, "weight": 50}, "1578637": {"name": "détailler des tournedos", "type": 1, "weight": 25}, "46788": {"name": "Eure", "type": 1, "weight": 2679}, "2348419": {"name": "::>66:140100>17:165199", "type": 8, "weight": 10}, "2352203": {"name": "plat à base de viande bovine", "type": 1, "weight": 25}, "2352223": {"name": "tournedos rossini", "type": 1, "weight": 25}, "213703": {"name": "tournedos Rossini", "type": 1, "weight": 94}, "257004": {"name": "pommes de terre sautées", "type": 1, "weight": 15}, "168329": {"name": "sauce béarnaise", "type": 1, "weight": 56}, "2488390": {"name": "châteaubriand", "type": 1, "weight": 27}, "152031": {"name": "foie gras", "type": 1, "weight": 533}, "115155": {"name": "foie", "type": 1, "weight": 1716}, "55342": {"name": "épais", "type": 1, "weight": 1387}, "26879": {"name": "Seine", "type": 1, "weight": 3497}, "64437": {"name": "boucherie", "type": 1, "weight": 1330}, "153936": {"name": "viande rouge", "type": 1, "weight": 484}, "146886": {"name": "Nom:Mas+InvPL", "type": 4, "weight": 50}, "160927": {"name": "morceau de viande", "type": 1, "weight": 171}, "59430": {"name": "lard", "type": 1, "weight": 342}, "39785": {"name": "tournedos", "type": 1, "weight": 112}, "143123": {"name": "tranche", "type": 1, "weight": 976}, "152552": {"name": "Cuisine", "type": 1, "weight": 226}, "191722": {"name": "steak haché", "type": 1, "weight": 257}, "128208": {"name": "vin rouge", "type": 1, "weight": 701}, "251716": {"name": "_INFO-MONOSEMIC", "type": 36, "weight": 50}, "408627": {"name": "Bois", "type": 1, "weight": 2071}, "167583": {"name": "commune française", "type": 1, "weight": 569}, "32322": {"name": "trancher", "type": 1, "weight": 1509}, "55572": {"name": "steak", "type": 1, "weight": 770}, "222079": {"name": "pavé>256609", "type": 1, "weight": 10}, "70900": {"name": "Auguste Escoffier", "type": 1, "weight": 50}, "415381": {"name": "Commun", "type": 1, "weight": 326}, "318495": {"name": "découpe du boeuf", "type": 1, "weight": 66}, "38188": {"name": "menu", "type": 1, "weight": 1168}, "145761": {"name": "seine", "type": 1, "weight": 903}, "140361": {"name": "Gras", "type": 1, "weight": 73}, "260475": {"name": "pièce noire", "type": 1, "weight": 52}, "2577247": {"name": "Filet", "type": 1, "weight": 29}, "227860": {"name": "sauce au poivre", "type": 1, "weight": 18}}, "relations": [{"node1": 39785, "node2": 8485, "type": 0, "weight": 30.0}, {"node1": 39785, "node2": 8485, "type": 666, "weight": 2.0}, {"node1": 39785, "node2": 13260, "type": 0, "weight": 33.0}, {"node1": 39785, "node2": 13890, "type": 0, "weight": 37.0}, {"node1": 39785, "node2": 14330, "type": 32, "weight": 189.0}, {"node1": 39785, "node2": 15763, "type": 0, "weight": 31.0}, {"node1": 39785, "node2": 16033, "type": 0, "weight": 59.0}, {"node1": 39785, "node2": 16033, "type": 3, "weight": 45.0}, {"node1": 39785, "node2": 16033, "type": 666, "weight": 2.0}, {"node1": 39785, "node2": 19636, "type": 0, "weight": 37.0}, {"node1": 39785, "node2": 22365, "type": 0, "weight": 30.0}, {"node1": 39785, "node2": 22365, "type": 5, "weight": 64.0}, {"node1": 39785, "node2": 22605, "type": 0, "weight": 31.0}, {"node1": 39785, "node2": 22772, "type": 0, "weight": 28.0}, {"node1": 39785, "node2": 26879, "type": 0, "weight": 1.0}, {"node1": 39785, "node2": 26979, "type": 0, "weight": 31.0}, {"node1": 39785, "node2": 27715, "type": 777, "weight": 10.0}, {"node1": 39785, "node2": 28453, "type": 32, "weight": 201.0}, {"node1": 39785, "node2": 32322, "type": 0, "weight": 11.0}, {"node1": 39785, "node2": 33634, "type": 0, "weight": 36.0}, {"node1": 39785, "node2": 36327, "type": 666, "weight": 2.0}, {"node1": 39785, "node2": 38188, "type": 666, "weight": 2.0}, {"node1": 39785, "node2": 39785, "type": 19, "weight": 51.0}, {"node1": 39785, "node2": 39785, "type": 170, "weight": 34.0}, {"node1": 39785, "node2": 41595, "type": 666, "weight": 2.0}, {"node1": 39785, "node2": 41642, "type": 0, "weight": 31.0}, {"node1": 39785, "node2": 42188, "type": 0, "weight": 41.0}, {"node1": 39785, "node2": 42188, "type": 5, "weight": 91.0}, {"node1": 39785, "node2": 43125, "type": 0, "weight": 39.0}, {"node1": 39785, "node2": 43125, "type": 3, "weight": 36.0}, {"node1": 39785, "node2": 46788, "type": 0, "weight": 1.0}, {"node1": 39785, "node2": 47417, "type": 0, "weight": 15.0}, {"node1": 39785, "node2": 47417, "type": 777, "weight": 10.0}, {"node1": 39785, "node2": 47669, "type": 777, "weight": 10.0}, {"node1": 39785, "node2": 49508, "type": 0, "weight": 34.0}, {"node1": 39785, "node2": 49508, "type": 5, "weight": 40.0}, {"node1": 39785, "node2": 55342, "type": 17, "weight": 34.0}, {"node1": 39785, "node2": 55342, "type": 666, "weight": 1.0}, {"node1": 39785, "node2": 55572, "type": 0, "weight": 46.0}, {"node1": 39785, "node2": 55834, "type": 0, "weight": 1.0}, {"node1": 39785, "node2": 56362, "type": 0, "weight": 1.0}, {"node1": 39785, "node2": 59430, "type": 0, "weight": 32.0}, {"node1": 39785, "node2": 60056, "type": 0, "weight": 38.0}, {"node1": 39785, "node2": 64437, "type": 0, "weight": 30.0}, {"node1": 39785, "node2": 64437, "type": 3, "weight": 26.0}, {"node1": 39785, "node2": 64437, "type": 15, "weight": 7.0}, {"node1": 39785, "node2": 64437, "type": 666, "weight": 1.0}, {"node1": 39785, "node2": 64441, "type": 777, "weight": 10.0}, {"node1": 39785, "node2": 70900, "type": 777, "weight": 10.0}, {"node1": 39785, "node2": 73091, "type": 0, "weight": 1.0}, {"node1": 39785, "node2": 74736, "type": 0, "weight": 37.0}, {"node1": 39785, "node2": 77419, "type": 0, "weight": 27.0}, {"node1": 39785, "node2": 79954, "type": 0, "weight": 38.0}, {"node1": 39785, "node2": 79954, "type": 666, "weight": 2.0}, {"node1": 39785, "node2": 80199, "type": 0, "weight": 31.0}, {"node1": 39785, "node2": 82147, "type": 17, "weight": 30.0}, {"node1": 39785, "node2": 82147, "type": 666, "weight": 1.0}, {"node1": 39785, "node2": 86356, "type": 0, "weight": 32.0}, {"node1": 39785, "node2": 89926, "type": 666, "weight": 2.0}, {"node1": 39785, "node2": 91657, "type": 0, "weight": 15.0}, {"node1": 39785, "node2": 91657, "type": 3, "weight": 37.0}, {"node1": 39785, "node2": 91691, "type": 32, "weight": 171.0}, {"node1": 39785, "node2": 93731, "type": 0, "weight": 2.0}, {"node1": 39785, "node2": 96256, "type": 0, "weight": 1.0}, {"node1": 39785, "node2": 97682, "type": 0, "weight": 44.0}, {"node1": 39785, "node2": 105441, "type": 0, "weight": 21.0}, {"node1": 39785, "node2": 108827, "type": 0, "weight": 33.0}, {"node1": 39785, "node2": 113902, "type": 0, "weight": 35.0}, {"node1": 39785, "node2": 113902, "type": 3, "weight": 28.0}, {"node1": 39785, "node2": 114701, "type": 0, "weight": 21.0}, {"node1": 39785, "node2": 115155, "type": 0, "weight": 1.0}, {"node1": 39785, "node2": 119873, "type": 0, "weight": 31.0}, {"node1": 39785, "node2": 120188, "type": 0, "weight": 3.0}, {"node1": 39785, "node2": 123307, "type": 0, "weight": 33.0}, {"node1": 39785, "node2": 124092, "type": 0, "weight": 30.0}, {"node1": 39785, "node2": 127547, "type": 666, "weight": 2.0}, {"node1": 39785, "node2": 128208, "type": 0, "weight": 33.0}, {"node1": 39785, "node2": 128208, "type": 666, "weight": 2.0}, {"node1": 39785, "node2": 130164, "type": 0, "weight": 38.0}, {"node1": 39785, "node2": 135982, "type": 0, "weight": 31.0}, {"node1": 39785, "node2": 138954, "type": 0, "weight": 32.0}, {"node1": 39785, "node2": 139597, "type": 0, "weight": 31.0}, {"node1": 39785, "node2": 140100, "type": 0, "weight": 58.0}, {"node1": 39785, "node2": 140100, "type": 50, "weight": 34.0}, {"node1": 39785, "node2": 140100, "type": 666, "weight": 2.0}, {"node1": 39785, "node2": 140361, "type": 0, "weight": 1.0}, {"node1": 39785, "node2": 140377, "type": 0, "weight": 34.0}, {"node1": 39785, "node2": 141518, "type": 777, "weight": 10.0}, {"node1": 39785, "node2": 141899, "type": 0, "weight": 37.0}, {"node1": 39785, "node2": 141899, "type": 777, "weight": 10.0}, {"node1": 39785, "node2": 143123, "type": 0, "weight": 58.0}, {"node1": 39785, "node2": 143123, "type": 6, "weight": 49.0}, {"node1": 39785, "node2": 143123, "type": 666, "weight": 1.0}, {"node1": 39785, "node2": 145761, "type": 0, "weight": 1.0}, {"node1": 39785, "node2": 146357, "type": 32, "weight": 66.0}, {"node1": 39785, "node2": 146885, "type": 4, "weight": 38.0}, {"node1": 39785, "node2": 146886, "type": 4, "weight": 51.0}, {"node1": 39785, "node2": 146887, "type": 4, "weight": 29.0}, {"node1": 39785, "node2": 151553, "type": 12, "weight": 21.0}, {"node1": 39785, "node2": 152031, "type": 0, "weight": 33.0}, {"node1": 39785, "node2": 152031, "type": 666, "weight": 2.0}, {"node1": 39785, "node2": 152031, "type": 777, "weight": 10.0}, {"node1": 39785, "node2": 152552, "type": 0, "weight": 41.0}, {"node1": 39785, "node2": 152552, "type": 35, "weight": 29.0}, {"node1": 39785, "node2": 153902, "type": 0, "weight": 29.0}, {"node1": 39785, "node2": 153936, "type": 0, "weight": 35.0}, {"node1": 39785, "node2": 153997, "type": 0, "weight": 27.0}, {"node1": 39785, "node2": 155774, "type": 0, "weight": 27.0}, {"node1": 39785, "node2": 156049, "type": 0, "weight": 27.0}, {"node1": 39785, "node2": 156387, "type": 0, "weight": 32.0}, {"node1": 39785, "node2": 156863, "type": 0, "weight": 30.0}, {"node1": 39785, "node2": 158591, "type": 777, "weight": 10.0}, {"node1": 39785, "node2": 160927, "type": 0, "weight": 43.0}, {"node1": 39785, "node2": 160927, "type": 6, "weight": 47.0}, {"node1": 39785, "node2": 160927, "type": 666, "weight": 1.0}, {"node1": 39785, "node2": 163988, "type": 0, "weight": 31.0}, {"node1": 39785, "node2": 163988, "type": 666, "weight": 2.0}, {"node1": 39785, "node2": 166491, "type": 0, "weight": 37.0}, {"node1": 39785, "node2": 166491, "type": 666, "weight": 2.0}, {"node1": 39785, "node2": 167583, "type": 777, "weight": 10.0}, {"node1": 39785, "node2": 168216, "type": 0, "weight": 20.0}, {"node1": 39785, "node2": 168329, "type": 0, "weight": 30.0}, {"node1": 39785, "node2": 168329, "type": 666, "weight": 2.0}, {"node1": 39785, "node2": 168792, "type": 777, "weight": 10.0}, {"node1": 39785, "node2": 171870, "type": 4, "weight": 47.0}, {"node1": 39785, "node2": 174932, "type": 777, "weight": 10.0}, {"node1": 39785, "node2": 177215, "type": 0, "weight": 29.0}, {"node1": 39785, "node2": 177215, "type": 5, "weight": 36.0}, {"node1": 39785, "node2": 191722, "type": 0, "weight": 37.0}, {"node1": 39785, "node2": 205835, "type": 0, "weight": 29.0}, {"node1": 39785, "node2": 205835, "type": 666, "weight": 2.0}, {"node1": 39785, "node2": 213703, "type": 0, "weight": 12.0}, {"node1": 39785, "node2": 213703, "type": 8, "weight": 36.0}, {"node1": 39785, "node2": 213703, "type": 11, "weight": 163.0}, {"node1": 39785, "node2": 214275, "type": 0, "weight": 43.0}, {"node1": 39785, "node2": 214275, "type": 3, "weight": 34.0}, {"node1": 39785, "node2": 215037, "type": 0, "weight": 41.0}, {"node1": 39785, "node2": 218746, "type": 15, "weight": 53.0}, {"node1": 39785, "node2": 222078, "type": 999, "weight": 11.0}, {"node1": 39785, "node2": 222079, "type": 999, "weight": 11.0}, {"node1": 39785, "node2": 222081, "type": 0, "weight": 21.0}, {"node1": 39785, "node2": 222082, "type": 999, "weight": 11.0}, {"node1": 39785, "node2": 223172, "type": 36, "weight": 1.0}, {"node1": 39785, "node2": 223173, "type": 36, "weight": 370.0}, {"node1": 39785, "node2": 225881, "type": 17, "weight": 25.0}, {"node1": 39785, "node2": 227860, "type": 0, "weight": 28.0}, {"node1": 39785, "node2": 227860, "type": 666, "weight": 2.0}, {"node1": 39785, "node2": 228897, "type": 0, "weight": 34.0}, {"node1": 39785, "node2": 235350, "type": 0, "weight": 20.0}, {"node1": 39785, "node2": 235993, "type": 0, "weight": 51.0}, {"node1": 39785, "node2": 235993, "type": 6, "weight": 16.0}, {"node1": 39785, "node2": 239128, "type": 0, "weight": 1000000.0}, {"node1": 39785, "node2": 241794, "type": 36, "weight": 118.0}, {"node1": 39785, "node2": 250629, "type": 0, "weight": 26.0}, {"node1": 39785, "node2": 251158, "type": 0, "weight": 51.0}, {"node1": 39785, "node2": 251158, "type": 6, "weight": 56.0}, {"node1": 39785, "node2": 251716, "type": 36, "weight": 28.0}, {"node1": 39785, "node2": 254876, "type": 36, "weight": 76.0}, {"node1": 39785, "node2": 254877, "type": 36, "weight": 24.0}, {"node1": 39785, "node2": 256015, "type": 0, "weight": 30.0}, {"node1": 39785, "node2": 257004, "type": 0, "weight": 32.0}, {"node1": 39785, "node2": 257004, "type": 666, "weight": 2.0}, {"node1": 39785, "node2": 260475, "type": 0, "weight": 22.0}, {"node1": 39785, "node2": 260477, "type": 0, "weight": 29.0}, {"node1": 39785, "node2": 276096, "type": 36, "weight": 31.0}, {"node1": 39785, "node2": 317322, "type": 36, "weight": 1.62}, {"node1": 39785, "node2": 317323, "type": 36, "weight": 0.57}, {"node1": 39785, "node2": 317324, "type": 36, "weight": 1.01}, {"node1": 39785, "node2": 317325, "type": 36, "weight": 0.74}, {"node1": 39785, "node2": 317326, "type": 36, "weight": 1.13}, {"node1": 39785, "node2": 317327, "type": 36, "weight": 0.72}, {"node1": 39785, "node2": 317329, "type": 36, "weight": 2.16}, {"node1": 39785, "node2": 318495, "type": 0, "weight": 31.0}, {"node1": 39785, "node2": 318495, "type": 3, "weight": 30.0}, {"node1": 39785, "node2": 390709, "type": 0, "weight": 28.0}, {"node1": 39785, "node2": 405513, "type": 0, "weight": 1.0}, {"node1": 39785, "node2": 408627, "type": 0, "weight": 1.0}, {"node1": 39785, "node2": 415381, "type": 0, "weight": 1.0}, {"node1": 39785, "node2": 422605, "type": 0, "weight": 1.0}, {"node1": 39785, "node2": 428313, "type": 0, "weight": 1.0}, {"node1": 39785, "node2": 438949, "type": 36, "weight": 25.0}, {"node1": 39785, "node2": 1560791, "type": 128, "weight": 3.0}, {"node1": 39785, "node2": 1560792, "type": 128, "weight": 3.0}, {"node1": 39785, "node2": 1578637, "type": 0, "weight": 22.0}, {"node1": 39785, "node2": 1578637, "type": 11, "weight": 60.0}, {"node1": 39785, "node2": 1912917, "type": 36, "weight": 41.0}, {"node1": 39785, "node2": 1972667, "type": 999, "weight": 7.0}, {"node1": 39785, "node2": 1972669, "type": 999, "weight": 7.0}, {"node1": 39785, "node2": 2348419, "type": 0, "weight": 20.0}, {"node1": 39785, "node2": 2352203, "type": 0, "weight": 30.0}, {"node1": 39785, "node2": 2352223, "type": 0, "weight": 5.0}, {"node1": 39785, "node2": 2352223, "type": 8, "weight": 38.0}, {"node1": 39785, "node2": 2352223, "type": 11, "weight": 53.0}, {"node1": 39785, "node2": 2352229, "type": 0, "weight": 1.0}, {"node1": 39785, "node2": 2488390, "type": 0, "weight": 30.0}, {"node1": 39785, "node2": 2488390, "type": 5, "weight": 44.0}, {"node1": 39785, "node2": 2577247, "type": 0, "weight": 1.0}, {"node1": 39785, "node2": 2577247, "type": 777, "weight": 10.0}, {"node1": 39785, "node2": 2578913, "type": 71, "weight": 27.0}, {"node1": 39785, "node2": 2578913, "type": 777, "weight": 10.0}]}