{"nodes": {"13864": {"name": "triphtongue", "type": 1, "weight": 52}, "21550": {"name": "polysyllabique", "type": 1, "weight": 51}, "21779": {"name": "A.E.I.O.U", "type": 1, "weight": 52}, "38762": {"name": "quadrisyllabique", "type": 1, "weight": 50}, "74397": {"name": "octosyllabique", "type": 1, "weight": 50}, "104535": {"name": "syllabème", "type": 1, "weight": 50}, "117717": {"name": "dodécasyllabe", "type": 1, "weight": 52}, "23573": {"name": "paragoge", "type": 1, "weight": 50}, "36646": {"name": "syllabisme", "type": 1, "weight": 50}, "64657": {"name": "i", "type": 1, "weight": 3688}, "102382": {"name": "latin", "type": 1, "weight": 3979}, "10356": {"name": "hongrois", "type": 1, "weight": 1967}, "73031": {"name": "paronomase", "type": 1, "weight": 54}, "105503": {"name": "allemand", "type": 1, "weight": 4575}, "59245": {"name": "pentasyllabe", "type": 1, "weight": 50}, "70628": {"name": "ïambe", "type": 1, "weight": 50}, "86686": {"name": "e", "type": 1, "weight": 3941}, "73205": {"name": "mandarin", "type": 1, "weight": 799}, "76305": {"name": "finnois", "type": 1, "weight": 64}, "14904": {"name": "monosyllabe", "type": 1, "weight": 50}, "4104": {"name": "tercet", "type": 1, "weight": 71}, "86142": {"name": "neutralisation", "type": 1, "weight": 227}, "12637": {"name": "Loi de Grimm", "type": 1, "weight": 51}, "17208": {"name": "sonorité", "type": 1, "weight": 571}, "114585": {"name": "oxyton", "type": 1, "weight": 50}, "9335": {"name": "phonème", "type": 1, "weight": 333}, "24034": {"name": "poème", "type": 1, "weight": 2864}, "96943": {"name": "coda", "type": 1, "weight": 52}, "88646": {"name": "Verner", "type": 1, "weight": 50}, "15324": {"name": "vocalique", "type": 1, "weight": 56}, "38998": {"name": "dissyllabique", "type": 1, "weight": 50}, "61648": {"name": "strophe", "type": 1, "weight": 350}, "103405": {"name": "indifférence", "type": 1, "weight": 981}, "11185": {"name": "trisyllabe", "type": 1, "weight": 50}, "58736": {"name": "addendum", "type": 1, "weight": 72}, "38608": {"name": "tétrasyllabe", "type": 1, "weight": 50}, "112507": {"name": "polysyllabe", "type": 1, "weight": 52}, "18467": {"name": "sémantiquement", "type": 1, "weight": 69}, "90934": {"name": "imparisyllabique", "type": 1, "weight": 50}, "77659": {"name": "suédois", "type": 1, "weight": 2698}, "92821": {"name": "semi-voyelle", "type": 1, "weight": 58}, "39891": {"name": "aperture", "type": 1, "weight": 53}, "118063": {"name": "proclise", "type": 1, "weight": 50}, "5426": {"name": "haïku", "type": 1, "weight": 91}, "24529": {"name": "hexamètre", "type": 1, "weight": 54}, "70689": {"name": "morphosyntaxique", "type": 1, "weight": 50}, "58170": {"name": "hauteur", "type": 1, "weight": 5873}, "94555": {"name": "phonétique", "type": 1, "weight": 2794}, "8923": {"name": "suffixes", "type": 1, "weight": 60}, "69169": {"name": "amuïssement", "type": 1, "weight": 52}, "7167": {"name": "aphérèse", "type": 1, "weight": 67}, "13587": {"name": "occidentale", "type": 1, "weight": 3495}, "42719": {"name": "arabe", "type": 1, "weight": 3875}, "32735": {"name": "poumons", "type": 1, "weight": 663}, "74897": {"name": "première", "type": 1, "weight": 6288}, "115763": {"name": "article", "type": 1, "weight": 14741}, "96312": {"name": "lecture", "type": 1, "weight": 7655}, "103658": {"name": "italien", "type": 1, "weight": 4257}, "60767": {"name": "formes", "type": 1, "weight": 6819}, "39313": {"name": "vocal", "type": 1, "weight": 326}, "22425": {"name": "espéranto", "type": 1, "weight": 80}, "21383": {"name": "débit", "type": 1, "weight": 3725}, "34898": {"name": "pied", "type": 1, "weight": 21583}, "74866": {"name": "tchèque", "type": 1, "weight": 2746}, "113464": {"name": "Français", "type": 1, "weight": 6081}, "66314": {"name": "former", "type": 1, "weight": 8823}, "32403": {"name": "russe", "type": 1, "weight": 4817}, "32528": {"name": "vers", "type": 1, "weight": 31199}, "54234": {"name": "écriture", "type": 1, "weight": 6510}, "73057": {"name": "initiale", "type": 1, "weight": 2894}, "83855": {"name": "sujet", "type": 1, "weight": 11320}, "112621": {"name": "poésie", "type": 1, "weight": 5666}, "75266": {"name": "langage", "type": 1, "weight": 11003}, "68295": {"name": "unité", "type": 1, "weight": 7821}, "71709": {"name": "acoustique", "type": 1, "weight": 711}, "34713": {"name": "japonais", "type": 1, "weight": 3878}, "51528": {"name": "son", "type": 1, "weight": 370438}, "34970": {"name": "attaque", "type": 1, "weight": 6307}, "14330": {"name": "satisfaction", "type": 1, "weight": 7748}, "23157": {"name": "linguistique", "type": 1, "weight": 5511}, "36757": {"name": "syntagme", "type": 1, "weight": 1796}, "116477": {"name": "personne", "type": 1, "weight": 35594}, "100640": {"name": "roman", "type": 1, "weight": 9230}, "51508": {"name": "alexandrin", "type": 1, "weight": 435}, "83072": {"name": "aspiration", "type": 1, "weight": 2157}, "115066": {"name": "prononciation", "type": 1, "weight": 2787}, "107902": {"name": "chanson", "type": 1, "weight": 5823}, "52119": {"name": "langue", "type": 1, "weight": 13308}, "91691": {"name": "surprise", "type": 1, "weight": 3439}, "28453": {"name": "bonheur", "type": 1, "weight": 16648}, "94538": {"name": "syllabe", "type": 1, "weight": 2102}, "66372": {"name": "texte", "type": 1, "weight": 16553}, "29362": {"name": "addenda", "type": 1, "weight": 52}, "84471": {"name": "sandhi", "type": 1, "weight": 50}, "113084": {"name": "thaï", "type": 1, "weight": 162}, "54194": {"name": "forte", "type": 1, "weight": 4465}, "79993": {"name": "anglais", "type": 1, "weight": 7660}, "96851": {"name": "pièce", "type": 1, "weight": 8573}, "51515": {"name": "voix", "type": 1, "weight": 29728}, "13861": {"name": "temps", "type": 1, "weight": 57698}, "104472": {"name": "mot-valise", "type": 1, "weight": 114}, "73509": {"name": "diphtongaison", "type": 1, "weight": 92}, "113268": {"name": "diphtongue", "type": 1, "weight": 58}, "49881": {"name": "néerlandais", "type": 1, "weight": 2824}, "14039": {"name": "lexème", "type": 1, "weight": 71}, "79526": {"name": "birman", "type": 1, "weight": 118}, "38078": {"name": "conjugaison", "type": 1, "weight": 1436}, "18716": {"name": "Antiquité", "type": 1, "weight": 1498}, "65421": {"name": "lituanien", "type": 1, "weight": 66}, "8084": {"name": "figure de rhétorique", "type": 1, "weight": 67}, "14832": {"name": "crase", "type": 1, "weight": 50}, "12753": {"name": "vocable", "type": 1, "weight": 175}, "64811": {"name": "enclise", "type": 1, "weight": 50}, "69516": {"name": "more", "type": 1, "weight": 1825}, "95049": {"name": "syllabaire", "type": 1, "weight": 78}, "14310": {"name": "syncope", "type": 1, "weight": 118}, "109114": {"name": "psycholinguistique", "type": 1, "weight": 107}, "114518": {"name": "schwa", "type": 1, "weight": 50}, "102314": {"name": "polonais", "type": 1, "weight": 2898}, "113384": {"name": "pluriel", "type": 1, "weight": 3000}, "90403": {"name": "brève", "type": 1, "weight": 1657}, "78869": {"name": "quantité", "type": 1, "weight": 7524}, "18532": {"name": "langues romanes", "type": 1, "weight": 68}, "77279": {"name": "tonique", "type": 1, "weight": 1769}, "108419": {"name": "vietnamien", "type": 1, "weight": 244}, "75299": {"name": "versification", "type": 1, "weight": 123}, "24177": {"name": "disjonction", "type": 1, "weight": 136}, "93995": {"name": "constitutif", "type": 1, "weight": 407}, "62830": {"name": "voyelles", "type": 1, "weight": 2488}, "74900": {"name": "consonnes", "type": 1, "weight": 2166}, "76103": {"name": "hindi", "type": 1, "weight": 128}, "99675": {"name": "apostrophe", "type": 1, "weight": 68}, "32132": {"name": "mot", "type": 1, "weight": 26564}, "111035": {"name": "bulgare", "type": 1, "weight": 118}, "66447": {"name": "tahitien", "type": 1, "weight": 66}, "40461": {"name": "breton", "type": 1, "weight": 3430}, "67131": {"name": "castillan", "type": 1, "weight": 63}, "41100": {"name": "flexion", "type": 1, "weight": 153}, "52749": {"name": "intonation", "type": 1, "weight": 254}, "41817": {"name": "occitan", "type": 1, "weight": 104}, "103343": {"name": "radical", "type": 1, "weight": 2930}, "35675": {"name": "sindhi", "type": 1, "weight": 50}, "108218": {"name": "voyelle", "type": 1, "weight": 2678}, "98268": {"name": "consonne", "type": 1, "weight": 2708}, "2041": {"name": "métrique", "type": 1, "weight": 1825}, "118090": {"name": "langues indo-européennes", "type": 1, "weight": 63}, "69876": {"name": "octosyllabe", "type": 1, "weight": 75}, "33808": {"name": "signifiant", "type": 1, "weight": 3197}, "115308": {"name": "accent", "type": 1, "weight": 3698}, "65586": {"name": "espagnol", "type": 1, "weight": 3746}, "17371": {"name": "catalan", "type": 1, "weight": 876}, "228": {"name": "élégie", "type": 1, "weight": 68}, "12602": {"name": "ictus", "type": 1, "weight": 50}, "33734": {"name": "quatrain", "type": 1, "weight": 94}, "57909": {"name": "langues slaves", "type": 1, "weight": 56}, "41079": {"name": "élision", "type": 1, "weight": 56}}, "relations": [{"node1": 94538, "node2": 228, "type": 0, "weight": 20.0}, {"node1": 94538, "node2": 2041, "type": 0, "weight": 26.0}, {"node1": 94538, "node2": 4104, "type": 0, "weight": 20.0}, {"node1": 94538, "node2": 5426, "type": 0, "weight": 211.0}, {"node1": 94538, "node2": 5426, "type": 666, "weight": 124.0}, {"node1": 94538, "node2": 7167, "type": 777, "weight": 10.0}, {"node1": 94538, "node2": 8084, "type": 0, "weight": 20.0}, {"node1": 94538, "node2": 8084, "type": 10, "weight": 25.0}, {"node1": 94538, "node2": 8923, "type": 777, "weight": 10.0}, {"node1": 94538, "node2": 9335, "type": 0, "weight": 27.0}, {"node1": 94538, "node2": 9335, "type": 666, "weight": 7.0}, {"node1": 94538, "node2": 9335, "type": 777, "weight": 10.0}, {"node1": 94538, "node2": 10356, "type": 777, "weight": 10.0}, {"node1": 94538, "node2": 11185, "type": 99, "weight": 26.0}, {"node1": 94538, "node2": 12602, "type": 0, "weight": 20.0}, {"node1": 94538, "node2": 12637, "type": 777, "weight": 10.0}, {"node1": 94538, "node2": 12753, "type": 10, "weight": 5.0}, {"node1": 94538, "node2": 13587, "type": 777, "weight": 10.0}, {"node1": 94538, "node2": 13861, "type": 777, "weight": 10.0}, {"node1": 94538, "node2": 13864, "type": 8, "weight": 38.0}, {"node1": 94538, "node2": 14039, "type": 777, "weight": 10.0}, {"node1": 94538, "node2": 14310, "type": 777, "weight": 10.0}, {"node1": 94538, "node2": 14330, "type": 32, "weight": 46.0}, {"node1": 94538, "node2": 14832, "type": 0, "weight": 23.0}, {"node1": 94538, "node2": 14904, "type": 0, "weight": 33.0}, {"node1": 94538, "node2": 14904, "type": 99, "weight": 34.0}, {"node1": 94538, "node2": 15324, "type": 777, "weight": 10.0}, {"node1": 94538, "node2": 17208, "type": 153, "weight": 25.0}, {"node1": 94538, "node2": 17371, "type": 777, "weight": 10.0}, {"node1": 94538, "node2": 18467, "type": 777, "weight": 10.0}, {"node1": 94538, "node2": 18532, "type": 777, "weight": 10.0}, {"node1": 94538, "node2": 18716, "type": 777, "weight": 10.0}, {"node1": 94538, "node2": 21383, "type": 0, "weight": 20.0}, {"node1": 94538, "node2": 21550, "type": 99, "weight": 26.0}, {"node1": 94538, "node2": 21779, "type": 0, "weight": 24.0}, {"node1": 94538, "node2": 22425, "type": 777, "weight": 10.0}, {"node1": 94538, "node2": 23157, "type": 0, "weight": 337.0}, {"node1": 94538, "node2": 23157, "type": 3, "weight": 529.0}, {"node1": 94538, "node2": 23157, "type": 777, "weight": 10.0}, {"node1": 94538, "node2": 23573, "type": 0, "weight": 20.0}, {"node1": 94538, "node2": 24034, "type": 0, "weight": 22.0}, {"node1": 94538, "node2": 24034, "type": 10, "weight": 64.0}, {"node1": 94538, "node2": 24177, "type": 777, "weight": 10.0}, {"node1": 94538, "node2": 24529, "type": 0, "weight": 20.0}, {"node1": 94538, "node2": 28453, "type": 32, "weight": 62.0}, {"node1": 94538, "node2": 29362, "type": 0, "weight": 10.0}, {"node1": 94538, "node2": 32132, "type": 0, "weight": 72.0}, {"node1": 94538, "node2": 32132, "type": 10, "weight": 90.0}, {"node1": 94538, "node2": 32132, "type": 666, "weight": 5.0}, {"node1": 94538, "node2": 32403, "type": 777, "weight": 10.0}, {"node1": 94538, "node2": 32528, "type": 0, "weight": 13.0}, {"node1": 94538, "node2": 32528, "type": 10, "weight": 60.0}, {"node1": 94538, "node2": 32528, "type": 666, "weight": 4.0}, {"node1": 94538, "node2": 32735, "type": 777, "weight": 10.0}, {"node1": 94538, "node2": 33734, "type": 0, "weight": 21.0}, {"node1": 94538, "node2": 33808, "type": 777, "weight": 10.0}, {"node1": 94538, "node2": 34713, "type": 777, "weight": 10.0}, {"node1": 94538, "node2": 34898, "type": 0, "weight": 48.0}, {"node1": 94538, "node2": 34898, "type": 5, "weight": 86.0}, {"node1": 94538, "node2": 34898, "type": 10, "weight": 59.0}, {"node1": 94538, "node2": 34970, "type": 777, "weight": 10.0}, {"node1": 94538, "node2": 35675, "type": 777, "weight": 10.0}, {"node1": 94538, "node2": 36646, "type": 0, "weight": 27.0}, {"node1": 94538, "node2": 36646, "type": 99, "weight": 29.0}, {"node1": 94538, "node2": 36757, "type": 0, "weight": 52.0}, {"node1": 94538, "node2": 36757, "type": 5, "weight": 61.0}, {"node1": 94538, "node2": 36757, "type": 777, "weight": 10.0}, {"node1": 94538, "node2": 38078, "type": 777, "weight": 10.0}, {"node1": 94538, "node2": 38608, "type": 99, "weight": 26.0}, {"node1": 94538, "node2": 38762, "type": 0, "weight": 22.0}, {"node1": 94538, "node2": 38998, "type": 99, "weight": 26.0}, {"node1": 94538, "node2": 39313, "type": 666, "weight": 3.0}, {"node1": 94538, "node2": 39891, "type": 777, "weight": 10.0}, {"node1": 94538, "node2": 40461, "type": 777, "weight": 10.0}, {"node1": 94538, "node2": 41079, "type": 777, "weight": 10.0}, {"node1": 94538, "node2": 41100, "type": 777, "weight": 10.0}, {"node1": 94538, "node2": 41817, "type": 777, "weight": 10.0}, {"node1": 94538, "node2": 42719, "type": 777, "weight": 10.0}, {"node1": 94538, "node2": 49881, "type": 777, "weight": 10.0}, {"node1": 94538, "node2": 51508, "type": 0, "weight": 24.0}, {"node1": 94538, "node2": 51515, "type": 666, "weight": 2.0}, {"node1": 94538, "node2": 51528, "type": 666, "weight": 7.0}, {"node1": 94538, "node2": 52119, "type": 666, "weight": 2.0}, {"node1": 94538, "node2": 52749, "type": 777, "weight": 10.0}, {"node1": 94538, "node2": 54194, "type": 17, "weight": 26.0}, {"node1": 94538, "node2": 54234, "type": 666, "weight": 4.0}, {"node1": 94538, "node2": 57909, "type": 777, "weight": 10.0}, {"node1": 94538, "node2": 58170, "type": 777, "weight": 10.0}, {"node1": 94538, "node2": 58736, "type": 0, "weight": 10.0}, {"node1": 94538, "node2": 59245, "type": 99, "weight": 26.0}, {"node1": 94538, "node2": 60767, "type": 777, "weight": 10.0}, {"node1": 94538, "node2": 61648, "type": 0, "weight": 26.0}, {"node1": 94538, "node2": 61648, "type": 10, "weight": 64.0}, {"node1": 94538, "node2": 62830, "type": 0, "weight": 4.0}, {"node1": 94538, "node2": 62830, "type": 9, "weight": 45.0}, {"node1": 94538, "node2": 64657, "type": 0, "weight": 8.0}, {"node1": 94538, "node2": 64657, "type": 9, "weight": 51.0}, {"node1": 94538, "node2": 64811, "type": 777, "weight": 10.0}, {"node1": 94538, "node2": 65421, "type": 777, "weight": 10.0}, {"node1": 94538, "node2": 65586, "type": 777, "weight": 10.0}, {"node1": 94538, "node2": 66314, "type": 0, "weight": 20.0}, {"node1": 94538, "node2": 66314, "type": 26, "weight": 100.0}, {"node1": 94538, "node2": 66372, "type": 0, "weight": 9.0}, {"node1": 94538, "node2": 66372, "type": 10, "weight": 90.0}, {"node1": 94538, "node2": 66447, "type": 777, "weight": 10.0}, {"node1": 94538, "node2": 67131, "type": 777, "weight": 10.0}, {"node1": 94538, "node2": 68295, "type": 0, "weight": 48.0}, {"node1": 94538, "node2": 68295, "type": 6, "weight": 56.0}, {"node1": 94538, "node2": 69169, "type": 777, "weight": 10.0}, {"node1": 94538, "node2": 69516, "type": 777, "weight": 10.0}, {"node1": 94538, "node2": 69876, "type": 0, "weight": 25.0}, {"node1": 94538, "node2": 69876, "type": 99, "weight": 26.0}, {"node1": 94538, "node2": 70628, "type": 0, "weight": 25.0}, {"node1": 94538, "node2": 70689, "type": 777, "weight": 10.0}, {"node1": 94538, "node2": 71709, "type": 777, "weight": 10.0}, {"node1": 94538, "node2": 73031, "type": 0, "weight": 20.0}, {"node1": 94538, "node2": 73057, "type": 17, "weight": 36.0}, {"node1": 94538, "node2": 73205, "type": 777, "weight": 10.0}, {"node1": 94538, "node2": 73509, "type": 777, "weight": 10.0}, {"node1": 94538, "node2": 74397, "type": 99, "weight": 26.0}, {"node1": 94538, "node2": 74866, "type": 777, "weight": 10.0}, {"node1": 94538, "node2": 74897, "type": 17, "weight": 61.0}, {"node1": 94538, "node2": 74900, "type": 777, "weight": 10.0}, {"node1": 94538, "node2": 75266, "type": 20, "weight": 40.0}, {"node1": 94538, "node2": 75266, "type": 666, "weight": 5.0}, {"node1": 94538, "node2": 75299, "type": 0, "weight": 21.0}, {"node1": 94538, "node2": 76103, "type": 777, "weight": 10.0}, {"node1": 94538, "node2": 76305, "type": 777, "weight": 10.0}, {"node1": 94538, "node2": 77279, "type": 0, "weight": 20.0}, {"node1": 94538, "node2": 77659, "type": 777, "weight": 10.0}, {"node1": 94538, "node2": 78869, "type": 777, "weight": 10.0}, {"node1": 94538, "node2": 79526, "type": 777, "weight": 10.0}, {"node1": 94538, "node2": 79993, "type": 777, "weight": 10.0}, {"node1": 94538, "node2": 83072, "type": 777, "weight": 10.0}, {"node1": 94538, "node2": 83855, "type": 777, "weight": 10.0}, {"node1": 94538, "node2": 84471, "type": 777, "weight": 10.0}, {"node1": 94538, "node2": 86142, "type": 777, "weight": 10.0}, {"node1": 94538, "node2": 86686, "type": 0, "weight": 8.0}, {"node1": 94538, "node2": 86686, "type": 9, "weight": 51.0}, {"node1": 94538, "node2": 88646, "type": 777, "weight": 10.0}, {"node1": 94538, "node2": 90403, "type": 0, "weight": 23.0}, {"node1": 94538, "node2": 90934, "type": 0, "weight": 21.0}, {"node1": 94538, "node2": 91691, "type": 32, "weight": 47.0}, {"node1": 94538, "node2": 92821, "type": 777, "weight": 10.0}, {"node1": 94538, "node2": 93995, "type": 0, "weight": 47.0}, {"node1": 94538, "node2": 94538, "type": 19, "weight": 51.0}, {"node1": 94538, "node2": 94555, "type": 0, "weight": 50.0}, {"node1": 94538, "node2": 94555, "type": 3, "weight": 45.0}, {"node1": 94538, "node2": 94555, "type": 777, "weight": 10.0}, {"node1": 94538, "node2": 95049, "type": 0, "weight": 46.0}, {"node1": 94538, "node2": 95049, "type": 10, "weight": 51.0}, {"node1": 94538, "node2": 95049, "type": 22, "weight": 35.0}, {"node1": 94538, "node2": 95049, "type": 99, "weight": 38.0}, {"node1": 94538, "node2": 96312, "type": 666, "weight": 2.0}, {"node1": 94538, "node2": 96851, "type": 0, "weight": 20.0}, {"node1": 94538, "node2": 96943, "type": 777, "weight": 10.0}, {"node1": 94538, "node2": 98268, "type": 0, "weight": 7.0}, {"node1": 94538, "node2": 98268, "type": 9, "weight": 60.0}, {"node1": 94538, "node2": 98268, "type": 666, "weight": 3.0}, {"node1": 94538, "node2": 99675, "type": 777, "weight": 10.0}, {"node1": 94538, "node2": 100640, "type": 0, "weight": 9.0}, {"node1": 94538, "node2": 100640, "type": 10, "weight": 70.0}, {"node1": 94538, "node2": 102314, "type": 777, "weight": 10.0}, {"node1": 94538, "node2": 102382, "type": 777, "weight": 10.0}, {"node1": 94538, "node2": 103343, "type": 777, "weight": 10.0}, {"node1": 94538, "node2": 103405, "type": 32, "weight": 51.0}, {"node1": 94538, "node2": 103658, "type": 777, "weight": 10.0}, {"node1": 94538, "node2": 104472, "type": 0, "weight": 51.0}, {"node1": 94538, "node2": 104472, "type": 10, "weight": 56.0}, {"node1": 94538, "node2": 104535, "type": 0, "weight": 26.0}, {"node1": 94538, "node2": 104535, "type": 99, "weight": 26.0}, {"node1": 94538, "node2": 105503, "type": 777, "weight": 10.0}, {"node1": 94538, "node2": 107902, "type": 0, "weight": 9.0}, {"node1": 94538, "node2": 107902, "type": 10, "weight": 60.0}, {"node1": 94538, "node2": 108218, "type": 0, "weight": 69.0}, {"node1": 94538, "node2": 108218, "type": 6, "weight": 51.0}, {"node1": 94538, "node2": 108218, "type": 9, "weight": 60.0}, {"node1": 94538, "node2": 108419, "type": 777, "weight": 10.0}, {"node1": 94538, "node2": 109114, "type": 777, "weight": 10.0}, {"node1": 94538, "node2": 111035, "type": 777, "weight": 10.0}, {"node1": 94538, "node2": 112507, "type": 0, "weight": 29.0}, {"node1": 94538, "node2": 112507, "type": 99, "weight": 30.0}, {"node1": 94538, "node2": 112621, "type": 0, "weight": 47.0}, {"node1": 94538, "node2": 112621, "type": 666, "weight": 6.0}, {"node1": 94538, "node2": 113084, "type": 777, "weight": 10.0}, {"node1": 94538, "node2": 113268, "type": 777, "weight": 10.0}, {"node1": 94538, "node2": 113384, "type": 777, "weight": 10.0}, {"node1": 94538, "node2": 113464, "type": 777, "weight": 10.0}, {"node1": 94538, "node2": 114518, "type": 777, "weight": 10.0}, {"node1": 94538, "node2": 114585, "type": 0, "weight": 21.0}, {"node1": 94538, "node2": 115066, "type": 0, "weight": 59.0}, {"node1": 94538, "node2": 115066, "type": 10, "weight": 63.0}, {"node1": 94538, "node2": 115066, "type": 666, "weight": 2.0}, {"node1": 94538, "node2": 115308, "type": 0, "weight": 27.0}, {"node1": 94538, "node2": 115308, "type": 666, "weight": 7.0}, {"node1": 94538, "node2": 115763, "type": 777, "weight": 10.0}, {"node1": 94538, "node2": 116477, "type": 777, "weight": 10.0}, {"node1": 94538, "node2": 117717, "type": 99, "weight": 26.0}, {"node1": 94538, "node2": 118063, "type": 777, "weight": 10.0}, {"node1": 94538, "node2": 118090, "type": 777, "weight": 10.0}]}